[{"date":"2025-02-05","name":"冀凯股份","code":"002691","remark":"净买: 1052.55万","price":0,"oprice":0,"cprice":0,"per":0,"per0":0,"per1":0,"per2":0,"per3":0,"per4":0,"per5":0,"per6":0,"per7":0,"per8":0,"per9":0,"per10":0,"per11":0},{"date":"2025-02-05","name":"普联软件","code":"300996","remark":"净卖: -1676.37万","price":0,"oprice":0,"cprice":0,"per":0,"per0":0,"per1":0,"per2":0,"per3":0,"per4":0,"per5":0,"per6":0,"per7":0,"per8":0,"per9":0,"per10":0,"per11":0},{"date":"2025-02-06","name":"冀东装备","code":"000856","remark":"净卖: -1713.11万","price":0,"oprice":0,"cprice":0,"per":0,"per0":0,"per1":0,"per2":0,"per3":0,"per4":0,"per5":0,"per6":0,"per7":0,"per8":0,"per9":0,"per10":0,"per11":0},{"date":"2025-02-06","name":"竞业达","code":"003005","remark":"净买: 1345.08万","price":0,"oprice":0,"cprice":0,"per":0,"per0":0,"per1":0,"per2":0,"per3":0,"per4":0,"per5":0,"per6":0,"per7":0,"per8":0,"per9":0,"per10":0,"per11":0},{"date":"2025-02-06","name":"慧为智能","code":"832876","remark":"净买: 641.00万","price":0,"oprice":0,"cprice":0,"per":0,"per0":0,"per1":0,"per2":0,"per3":0,"per4":0,"per5":0,"per6":0,"per7":0,"per8":0,"per9":0,"per10":0,"per11":0},{"date":"2025-02-06","name":"瀛通通讯","code":"002861","remark":"净买: 1320.43万","price":0,"oprice":0,"cprice":0,"per":0,"per0":0,"per1":0,"per2":0,"per3":0,"per4":0,"per5":0,"per6":0,"per7":0,"per8":0,"per9":0,"per10":0,"per11":0},{"date":"2025-02-06","name":"冀凯股份","code":"002691","remark":"净卖: -1080.38万","price":0,"oprice":0,"cprice":0,"per":0,"per0":0,"per1":0,"per2":0,"per3":0,"per4":0,"per5":0,"per6":0,"per7":0,"per8":0,"per9":0,"per10":0,"per11":0},{"date":"2025-02-07","name":"竞业达","code":"003005","remark":"净卖: -1297.76万","price":0,"oprice":0,"cprice":0,"per":0,"per0":0,"per1":0,"per2":0,"per3":0,"per4":0,"per5":0,"per6":0,"per7":0,"per8":0,"per9":0,"per10":0,"per11":0},{"date":"2025-02-07","name":"并行科技","code":"839493","remark":"净买: 1657.41万","price":0,"oprice":0,"cprice":0,"per":0,"per0":0,"per1":0,"per2":0,"per3":0,"per4":0,"per5":0,"per6":0,"per7":0,"per8":0,"per9":0,"per10":0,"per11":0},{"date":"2025-02-07","name":"*ST普利","code":"300630","remark":"净买: 234.78万","price":0,"oprice":0,"cprice":0,"per":0,"per0":0,"per1":0,"per2":0,"per3":0,"per4":0,"per5":0,"per6":0,"per7":0,"per8":0,"per9":0,"per10":0,"per11":0},{"date":"2025-02-10","name":"华阳变速","code":"839946","remark":"净卖: -510.69万","price":0,"oprice":0,"cprice":0,"per":0,"per0":0,"per1":0,"per2":0,"per3":0,"per4":0,"per5":0,"per6":0,"per7":0,"per8":0,"per9":0,"per10":0,"per11":0},{"date":"2025-02-10","name":"瀛通通讯","code":"002861","remark":"净卖: -2865.97万","price":0,"oprice":0,"cprice":0,"per":0,"per0":0,"per1":0,"per2":0,"per3":0,"per4":0,"per5":0,"per6":0,"per7":0,"per8":0,"per9":0,"per10":0,"per11":0},{"date":"2025-02-10","name":"并行科技","code":"839493","remark":"净买: 1963.27万","price":0,"oprice":0,"cprice":0,"per":0,"per0":0,"per1":0,"per2":0,"per3":0,"per4":0,"per5":0,"per6":0,"per7":0,"per8":0,"per9":0,"per10":0,"per11":0},{"date":"2025-02-11","name":"冀凯股份","code":"002691","remark":"净买: 1155.24万","price":0,"oprice":0,"cprice":0,"per":0,"per0":0,"per1":0,"per2":0,"per3":0,"per4":0,"per5":0,"per6":0,"per7":0,"per8":0,"per9":0,"per10":0,"per11":0},{"date":"2025-02-11","name":"广脉科技","code":"838924","remark":"净买: 976.79万","price":0,"oprice":0,"cprice":0,"per":0,"per0":0,"per1":0,"per2":0,"per3":0,"per4":0,"per5":0,"per6":0,"per7":0,"per8":0,"per9":0,"per10":0,"per11":0},{"date":"2025-02-11","name":"中草香料","code":"920016","remark":"净买: 301.48万","price":0,"oprice":0,"cprice":0,"per":0,"per0":0,"per1":0,"per2":0,"per3":0,"per4":0,"per5":0,"per6":0,"per7":0,"per8":0,"per9":0,"per10":0,"per11":0},{"date":"2025-02-11","name":"亚香股份","code":"301220","remark":"净买: 1617.16万","price":0,"oprice":0,"cprice":0,"per":0,"per0":0,"per1":0,"per2":0,"per3":0,"per4":0,"per5":0,"per6":0,"per7":0,"per8":0,"per9":0,"per10":0,"per11":0},{"date":"2025-02-11","name":"航锦科技","code":"000818","remark":"净买: 2995.37万","price":0,"oprice":0,"cprice":0,"per":0,"per0":0,"per1":0,"per2":0,"per3":0,"per4":0,"per5":0,"per6":0,"per7":0,"per8":0,"per9":0,"per10":0,"per11":0},{"date":"2025-02-11","name":"杭州高新","code":"300478","remark":"净买: 1084.21万","price":0,"oprice":0,"cprice":0,"per":0,"per0":0,"per1":0,"per2":0,"per3":0,"per4":0,"per5":0,"per6":0,"per7":0,"per8":0,"per9":0,"per10":0,"per11":0},{"date":"2025-02-12","name":"依米康","code":"300249","remark":"净买: 2916.42万","price":0,"oprice":0,"cprice":0,"per":0,"per0":0,"per1":0,"per2":0,"per3":0,"per4":0,"per5":0,"per6":0,"per7":0,"per8":0,"per9":0,"per10":0,"per11":0},{"date":"2025-02-12","name":"金帝股份","code":"603270","remark":"净卖: -1516.07万","price":0,"oprice":0,"cprice":0,"per":0,"per0":0,"per1":0,"per2":0,"per3":0,"per4":0,"per5":0,"per6":0,"per7":0,"per8":0,"per9":0,"per10":0,"per11":0},{"date":"2025-02-13","name":"依米康","code":"300249","remark":"净卖: -32.01万","price":0,"oprice":0,"cprice":0,"per":0,"per0":0,"per1":0,"per2":0,"per3":0,"per4":0,"per5":0,"per6":0,"per7":0,"per8":0,"per9":0,"per10":0,"per11":0},{"date":"2025-02-14","name":"威派格","code":"603956","remark":"净买: 1656.59万","price":0,"oprice":0,"cprice":0,"per":0,"per0":0,"per1":0,"per2":0,"per3":0,"per4":0,"per5":0,"per6":0,"per7":0,"per8":0,"per9":0,"per10":0,"per11":0},{"date":"2025-02-14","name":"云创数据","code":"835305","remark":"净买: 1294.89万","price":0,"oprice":0,"cprice":0,"per":0,"per0":0,"per1":0,"per2":0,"per3":0,"per4":0,"per5":0,"per6":0,"per7":0,"per8":0,"per9":0,"per10":0,"per11":0},{"date":"2025-02-17","name":"麦迪科技","code":"603990","remark":"净卖: -2264.10万","price":0,"oprice":0,"cprice":0,"per":0,"per0":0,"per1":0,"per2":0,"per3":0,"per4":0,"per5":0,"per6":0,"per7":0,"per8":0,"per9":0,"per10":0,"per11":0},{"date":"2025-02-17","name":"派诺科技","code":"831175","remark":"净买: 1616.66万","price":0,"oprice":0,"cprice":0,"per":0,"per0":0,"per1":0,"per2":0,"per3":0,"per4":0,"per5":0,"per6":0,"per7":0,"per8":0,"per9":0,"per10":0,"per11":0},{"date":"2025-02-17","name":"杭州高新","code":"300478","remark":"净买: 1515.64万","price":0,"oprice":0,"cprice":0,"per":0,"per0":0,"per1":0,"per2":0,"per3":0,"per4":0,"per5":0,"per6":0,"per7":0,"per8":0,"per9":0,"per10":0,"per11":0},{"date":"2025-02-18","name":"宏景科技","code":"301396","remark":"净买: 2006.03万","price":0,"oprice":0,"cprice":0,"per":0,"per0":0,"per1":0,"per2":0,"per3":0,"per4":0,"per5":0,"per6":0,"per7":0,"per8":0,"per9":0,"per10":0,"per11":0},{"date":"2025-02-18","name":"杭州高新","code":"300478","remark":"净卖: -1699.57万","price":0,"oprice":0,"cprice":0,"per":0,"per0":0,"per1":0,"per2":0,"per3":0,"per4":0,"per5":0,"per6":0,"per7":0,"per8":0,"per9":0,"per10":0,"per11":0},{"date":"2025-02-18","name":"南兴股份","code":"002757","remark":"净买: 3441.52万","price":0,"oprice":0,"cprice":0,"per":0,"per0":0,"per1":0,"per2":0,"per3":0,"per4":0,"per5":0,"per6":0,"per7":0,"per8":0,"per9":0,"per10":0,"per11":0},{"date":"2025-02-19","name":"航锦科技","code":"000818","remark":"净买: 4084.65万","price":0,"oprice":0,"cprice":0,"per":0,"per0":0,"per1":0,"per2":0,"per3":0,"per4":0,"per5":0,"per6":0,"per7":0,"per8":0,"per9":0,"per10":0,"per11":0},{"date":"2025-02-19","name":"派诺科技","code":"831175","remark":"净卖: -847.57万","price":0,"oprice":0,"cprice":0,"per":0,"per0":0,"per1":0,"per2":0,"per3":0,"per4":0,"per5":0,"per6":0,"per7":0,"per8":0,"per9":0,"per10":0,"per11":0},{"date":"2025-02-19","name":"福鞍股份","code":"603315","remark":"净卖: -406.34万","price":0,"oprice":0,"cprice":0,"per":0,"per0":0,"per1":0,"per2":0,"per3":0,"per4":0,"per5":0,"per6":0,"per7":0,"per8":0,"per9":0,"per10":0,"per11":0},{"date":"2025-02-19","name":"禾盛新材","code":"002290","remark":"净买: 1679.17万","price":0,"oprice":0,"cprice":0,"per":0,"per0":0,"per1":0,"per2":0,"per3":0,"per4":0,"per5":0,"per6":0,"per7":0,"per8":0,"per9":0,"per10":0,"per11":0},{"date":"2025-02-19","name":"兴通股份","code":"603209","remark":"净买: 1786.20万","price":0,"oprice":0,"cprice":0,"per":0,"per0":0,"per1":0,"per2":0,"per3":0,"per4":0,"per5":0,"per6":0,"per7":0,"per8":0,"per9":0,"per10":0,"per11":0},{"date":"2025-02-19","name":"华嵘控股","code":"600421","remark":"净卖: -280.31万","price":0,"oprice":0,"cprice":0,"per":0,"per0":0,"per1":0,"per2":0,"per3":0,"per4":0,"per5":0,"per6":0,"per7":0,"per8":0,"per9":0,"per10":0,"per11":0},{"date":"2025-02-20","name":"纬达光电","code":"873001","remark":"净买: 885.61万","price":0,"oprice":0,"cprice":0,"per":0,"per0":0,"per1":0,"per2":0,"per3":0,"per4":0,"per5":0,"per6":0,"per7":0,"per8":0,"per9":0,"per10":0,"per11":0},{"date":"2025-02-20","name":"明月镜片","code":"301101","remark":"净买: 1972.04万","price":0,"oprice":0,"cprice":0,"per":0,"per0":0,"per1":0,"per2":0,"per3":0,"per4":0,"per5":0,"per6":0,"per7":0,"per8":0,"per9":0,"per10":0,"per11":0},{"date":"2025-02-20","name":"航锦科技","code":"000818","remark":"净卖: -2612.94万","price":0,"oprice":0,"cprice":0,"per":0,"per0":0,"per1":0,"per2":0,"per3":0,"per4":0,"per5":0,"per6":0,"per7":0,"per8":0,"per9":0,"per10":0,"per11":0},{"date":"2025-02-20","name":"宏景科技","code":"301396","remark":"净卖: -1163.64万","price":0,"oprice":0,"cprice":0,"per":0,"per0":0,"per1":0,"per2":0,"per3":0,"per4":0,"per5":0,"per6":0,"per7":0,"per8":0,"per9":0,"per10":0,"per11":0},{"date":"2025-02-21","name":"杭齿前进","code":"601177","remark":"净买: 2547.55万","price":0,"oprice":0,"cprice":0,"per":0,"per0":0,"per1":0,"per2":0,"per3":0,"per4":0,"per5":0,"per6":0,"per7":0,"per8":0,"per9":0,"per10":0,"per11":0},{"date":"2025-02-21","name":"威派格","code":"603956","remark":"净买: 2696.03万","price":0,"oprice":0,"cprice":0,"per":0,"per0":0,"per1":0,"per2":0,"per3":0,"per4":0,"per5":0,"per6":0,"per7":0,"per8":0,"per9":0,"per10":0,"per11":0},{"date":"2025-02-21","name":"禾盛新材","code":"002290","remark":"净卖: -1905.84万","price":0,"oprice":0,"cprice":0,"per":0,"per0":0,"per1":0,"per2":0,"per3":0,"per4":0,"per5":0,"per6":0,"per7":0,"per8":0,"per9":0,"per10":0,"per11":0},{"date":"2025-02-24","name":"华丰股份","code":"605100","remark":"净买: 1644.46万","price":0,"oprice":0,"cprice":0,"per":0,"per0":0,"per1":0,"per2":0,"per3":0,"per4":0,"per5":0,"per6":0,"per7":0,"per8":0,"per9":0,"per10":0,"per11":0},{"date":"2025-02-24","name":"盈峰环境","code":"000967","remark":"净卖: -1891.86万","price":0,"oprice":0,"cprice":0,"per":0,"per0":0,"per1":0,"per2":0,"per3":0,"per4":0,"per5":0,"per6":0,"per7":0,"per8":0,"per9":0,"per10":0,"per11":0},{"date":"2025-02-24","name":"威派格","code":"603956","remark":"净卖: -2700.42万","price":0,"oprice":0,"cprice":0,"per":0,"per0":0,"per1":0,"per2":0,"per3":0,"per4":0,"per5":0,"per6":0,"per7":0,"per8":0,"per9":0,"per10":0,"per11":0},{"date":"2025-02-25","name":"杭钢股份","code":"600126","remark":"净买: 7756.62万","price":0,"oprice":0,"cprice":0,"per":0,"per0":0,"per1":0,"per2":0,"per3":0,"per4":0,"per5":0,"per6":0,"per7":0,"per8":0,"per9":0,"per10":0,"per11":0},{"date":"2025-02-25","name":"天玑科技","code":"300245","remark":"净买: 2415.95万","price":0,"oprice":0,"cprice":0,"per":0,"per0":0,"per1":0,"per2":0,"per3":0,"per4":0,"per5":0,"per6":0,"per7":0,"per8":0,"per9":0,"per10":0,"per11":0},{"date":"2025-02-26","name":"杭钢股份","code":"600126","remark":"净买: 1.13亿","price":0,"oprice":0,"cprice":0,"per":0,"per0":0,"per1":0,"per2":0,"per3":0,"per4":0,"per5":0,"per6":0,"per7":0,"per8":0,"per9":0,"per10":0,"per11":0},{"date":"2025-02-26","name":"圣阳股份","code":"002580","remark":"净买: 1569.55万","price":0,"oprice":0,"cprice":0,"per":0,"per0":0,"per1":0,"per2":0,"per3":0,"per4":0,"per5":0,"per6":0,"per7":0,"per8":0,"per9":0,"per10":0,"per11":0},{"date":"2025-02-26","name":"华丰股份","code":"605100","remark":"净买: 1261.76万","price":0,"oprice":0,"cprice":0,"per":0,"per0":0,"per1":0,"per2":0,"per3":0,"per4":0,"per5":0,"per6":0,"per7":0,"per8":0,"per9":0,"per10":0,"per11":0},{"date":"2025-02-27","name":"万达轴承","code":"920002","remark":"净买: 1571.67万","price":0,"oprice":0,"cprice":0,"per":0,"per0":0,"per1":0,"per2":0,"per3":0,"per4":0,"per5":0,"per6":0,"per7":0,"per8":0,"per9":0,"per10":0,"per11":0},{"date":"2025-02-28","name":"春光药装","code":"838810","remark":"净买: 955.33万","price":0,"oprice":0,"cprice":0,"per":0,"per0":0,"per1":0,"per2":0,"per3":0,"per4":0,"per5":0,"per6":0,"per7":0,"per8":0,"per9":0,"per10":0,"per11":0},{"date":"2025-02-28","name":"万达轴承","code":"920002","remark":"净卖: -1806.91万","price":0,"oprice":0,"cprice":0,"per":0,"per0":0,"per1":0,"per2":0,"per3":0,"per4":0,"per5":0,"per6":0,"per7":0,"per8":0,"per9":0,"per10":0,"per11":0},{"date":"2025-03-03","name":"德尔股份","code":"300473","remark":"净买: 4128.92万","price":0,"oprice":0,"cprice":0,"per":0,"per0":0,"per1":0,"per2":0,"per3":0,"per4":0,"per5":0,"per6":0,"per7":0,"per8":0,"per9":0,"per10":0,"per11":0},{"date":"2025-03-03","name":"灵鸽科技","code":"833284","remark":"净买: 255.72万","price":0,"oprice":0,"cprice":0,"per":0,"per0":0,"per1":0,"per2":0,"per3":0,"per4":0,"per5":0,"per6":0,"per7":0,"per8":0,"per9":0,"per10":0,"per11":0},{"date":"2025-03-03","name":"华丰股份","code":"605100","remark":"净卖: -4277.39万","price":0,"oprice":0,"cprice":0,"per":0,"per0":0,"per1":0,"per2":0,"per3":0,"per4":0,"per5":0,"per6":0,"per7":0,"per8":0,"per9":0,"per10":0,"per11":0},{"date":"2025-03-04","name":"天正电气","code":"605066","remark":"净买: 2791.83万","price":0,"oprice":0,"cprice":0,"per":0,"per0":0,"per1":0,"per2":0,"per3":0,"per4":0,"per5":0,"per6":0,"per7":0,"per8":0,"per9":0,"per10":0,"per11":0},{"date":"2025-03-04","name":"襄阳轴承","code":"000678","remark":"净买: 2232.25万","price":0,"oprice":0,"cprice":0,"per":0,"per0":0,"per1":0,"per2":0,"per3":0,"per4":0,"per5":0,"per6":0,"per7":0,"per8":0,"per9":0,"per10":0,"per11":0},{"date":"2025-03-04","name":"浩淼科技","code":"831856","remark":"净买: 1118.70万","price":0,"oprice":0,"cprice":0,"per":0,"per0":0,"per1":0,"per2":0,"per3":0,"per4":0,"per5":0,"per6":0,"per7":0,"per8":0,"per9":0,"per10":0,"per11":0},{"date":"2025-03-04","name":"晟楠科技","code":"837006","remark":"净买: 1298.01万","price":0,"oprice":0,"cprice":0,"per":0,"per0":0,"per1":0,"per2":0,"per3":0,"per4":0,"per5":0,"per6":0,"per7":0,"per8":0,"per9":0,"per10":0,"per11":0},{"date":"2025-03-05","name":"晟楠科技","code":"837006","remark":"净卖: -1310.52万","price":0,"oprice":0,"cprice":0,"per":0,"per0":0,"per1":0,"per2":0,"per3":0,"per4":0,"per5":0,"per6":0,"per7":0,"per8":0,"per9":0,"per10":0,"per11":0},{"date":"2025-03-05","name":"天正电气","code":"605066","remark":"净卖: -3060.88万","price":0,"oprice":0,"cprice":0,"per":0,"per0":0,"per1":0,"per2":0,"per3":0,"per4":0,"per5":0,"per6":0,"per7":0,"per8":0,"per9":0,"per10":0,"per11":0},{"date":"2025-03-05","name":"浩淼科技","code":"831856","remark":"净卖: -921.88万","price":0,"oprice":0,"cprice":0,"per":0,"per0":0,"per1":0,"per2":0,"per3":0,"per4":0,"per5":0,"per6":0,"per7":0,"per8":0,"per9":0,"per10":0,"per11":0},{"date":"2025-03-05","name":"云鼎科技","code":"000409","remark":"净买: 989.17万","price":0,"oprice":0,"cprice":0,"per":0,"per0":0,"per1":0,"per2":0,"per3":0,"per4":0,"per5":0,"per6":0,"per7":0,"per8":0,"per9":0,"per10":0,"per11":0},{"date":"2025-03-05","name":"征和工业","code":"003033","remark":"净卖: -2093.22万","price":0,"oprice":0,"cprice":0,"per":0,"per0":0,"per1":0,"per2":0,"per3":0,"per4":0,"per5":0,"per6":0,"per7":0,"per8":0,"per9":0,"per10":0,"per11":0},{"date":"2025-03-05","name":"莱赛激光","code":"871263","remark":"净买: 1974.46万","price":0,"oprice":0,"cprice":0,"per":0,"per0":0,"per1":0,"per2":0,"per3":0,"per4":0,"per5":0,"per6":0,"per7":0,"per8":0,"per9":0,"per10":0,"per11":0},{"date":"2025-03-06","name":"蓝色光标","code":"300058","remark":"净买: 8225.05万","price":0,"oprice":0,"cprice":0,"per":0,"per0":0,"per1":0,"per2":0,"per3":0,"per4":0,"per5":0,"per6":0,"per7":0,"per8":0,"per9":0,"per10":0,"per11":0},{"date":"2025-03-06","name":"杭齿前进","code":"601177","remark":"净买: 5677.41万","price":0,"oprice":0,"cprice":0,"per":0,"per0":0,"per1":0,"per2":0,"per3":0,"per4":0,"per5":0,"per6":0,"per7":0,"per8":0,"per9":0,"per10":0,"per11":0},{"date":"2025-03-07","name":"华丰股份","code":"605100","remark":"净卖: -1944.03万","price":0,"oprice":0,"cprice":0,"per":0,"per0":0,"per1":0,"per2":0,"per3":0,"per4":0,"per5":0,"per6":0,"per7":0,"per8":0,"per9":0,"per10":0,"per11":0},{"date":"2025-03-07","name":"群兴玩具","code":"002575","remark":"净卖: -3225.14万","price":0,"oprice":0,"cprice":0,"per":0,"per0":0,"per1":0,"per2":0,"per3":0,"per4":0,"per5":0,"per6":0,"per7":0,"per8":0,"per9":0,"per10":0,"per11":0},{"date":"2025-03-10","name":"京城股份","code":"600860","remark":"净买: 1911.21万","price":0,"oprice":0,"cprice":0,"per":0,"per0":0,"per1":0,"per2":0,"per3":0,"per4":0,"per5":0,"per6":0,"per7":0,"per8":0,"per9":0,"per10":0,"per11":0},{"date":"2025-03-10","name":"信隆健康","code":"002105","remark":"净买: 4731.65万","price":0,"oprice":0,"cprice":0,"per":0,"per0":0,"per1":0,"per2":0,"per3":0,"per4":0,"per5":0,"per6":0,"per7":0,"per8":0,"per9":0,"per10":0,"per11":0},{"date":"2025-03-10","name":"悦心健康","code":"002162","remark":"净买: 1807.50万","price":0,"oprice":0,"cprice":0,"per":0,"per0":0,"per1":0,"per2":0,"per3":0,"per4":0,"per5":0,"per6":0,"per7":0,"per8":0,"per9":0,"per10":0,"per11":0},{"date":"2025-03-10","name":"森远股份","code":"300210","remark":"净卖: -712.33万","price":0,"oprice":0,"cprice":0,"per":0,"per0":0,"per1":0,"per2":0,"per3":0,"per4":0,"per5":0,"per6":0,"per7":0,"per8":0,"per9":0,"per10":0,"per11":0},{"date":"2025-03-11","name":"汉朔科技","code":"301275","remark":"净买: 2303.32万","price":0,"oprice":0,"cprice":0,"per":0,"per0":0,"per1":0,"per2":0,"per3":0,"per4":0,"per5":0,"per6":0,"per7":0,"per8":0,"per9":0,"per10":0,"per11":0},{"date":"2025-03-11","name":"京城股份","code":"600860","remark":"净卖: -1707.86万","price":0,"oprice":0,"cprice":0,"per":0,"per0":0,"per1":0,"per2":0,"per3":0,"per4":0,"per5":0,"per6":0,"per7":0,"per8":0,"per9":0,"per10":0,"per11":0},{"date":"2025-03-11","name":"卓兆点胶","code":"873726","remark":"净买: 945.93万","price":0,"oprice":0,"cprice":0,"per":0,"per0":0,"per1":0,"per2":0,"per3":0,"per4":0,"per5":0,"per6":0,"per7":0,"per8":0,"per9":0,"per10":0,"per11":0},{"date":"2025-03-11","name":"华丰股份","code":"605100","remark":"净买: 2937.70万","price":0,"oprice":0,"cprice":0,"per":0,"per0":0,"per1":0,"per2":0,"per3":0,"per4":0,"per5":0,"per6":0,"per7":0,"per8":0,"per9":0,"per10":0,"per11":0},{"date":"2025-03-12","name":"杭电股份","code":"603618","remark":"净买: 1216.67万","price":0,"oprice":0,"cprice":0,"per":0,"per0":0,"per1":0,"per2":0,"per3":0,"per4":0,"per5":0,"per6":0,"per7":0,"per8":0,"per9":0,"per10":0,"per11":0},{"date":"2025-03-12","name":"卓兆点胶","code":"873726","remark":"净卖: -955.55万","price":0,"oprice":0,"cprice":0,"per":0,"per0":0,"per1":0,"per2":0,"per3":0,"per4":0,"per5":0,"per6":0,"per7":0,"per8":0,"per9":0,"per10":0,"per11":0},{"date":"2025-03-12","name":"正和生态","code":"605069","remark":"净买: 1237.42万","price":0,"oprice":0,"cprice":0,"per":0,"per0":0,"per1":0,"per2":0,"per3":0,"per4":0,"per5":0,"per6":0,"per7":0,"per8":0,"per9":0,"per10":0,"per11":0},{"date":"2025-03-12","name":"信隆健康","code":"002105","remark":"净卖: -5295.79万","price":0,"oprice":0,"cprice":0,"per":0,"per0":0,"per1":0,"per2":0,"per3":0,"per4":0,"per5":0,"per6":0,"per7":0,"per8":0,"per9":0,"per10":0,"per11":0},{"date":"2025-03-12","name":"华丰股份","code":"605100","remark":"净卖: -1663.87万","price":0,"oprice":0,"cprice":0,"per":0,"per0":0,"per1":0,"per2":0,"per3":0,"per4":0,"per5":0,"per6":0,"per7":0,"per8":0,"per9":0,"per10":0,"per11":0},{"date":"2025-03-12","name":"华原股份","code":"838837","remark":"净买: 840.65万","price":0,"oprice":0,"cprice":0,"per":0,"per0":0,"per1":0,"per2":0,"per3":0,"per4":0,"per5":0,"per6":0,"per7":0,"per8":0,"per9":0,"per10":0,"per11":0},{"date":"2025-03-13","name":"克莱特","code":"831689","remark":"净买: 1062.69万","price":0,"oprice":0,"cprice":0,"per":0,"per0":0,"per1":0,"per2":0,"per3":0,"per4":0,"per5":0,"per6":0,"per7":0,"per8":0,"per9":0,"per10":0,"per11":0},{"date":"2025-03-13","name":"力鼎光电","code":"605118","remark":"净买: 1866.35万","price":0,"oprice":0,"cprice":0,"per":0,"per0":0,"per1":0,"per2":0,"per3":0,"per4":0,"per5":0,"per6":0,"per7":0,"per8":0,"per9":0,"per10":0,"per11":0},{"date":"2025-03-13","name":"华丰股份","code":"605100","remark":"净买: 740.73万","price":0,"oprice":0,"cprice":0,"per":0,"per0":0,"per1":0,"per2":0,"per3":0,"per4":0,"per5":0,"per6":0,"per7":0,"per8":0,"per9":0,"per10":0,"per11":0},{"date":"2025-03-13","name":"正和生态","code":"605069","remark":"净卖: -1123.78万","price":0,"oprice":0,"cprice":0,"per":0,"per0":0,"per1":0,"per2":0,"per3":0,"per4":0,"per5":0,"per6":0,"per7":0,"per8":0,"per9":0,"per10":0,"per11":0},{"date":"2025-03-13","name":"新柴股份","code":"301032","remark":"净买: 1892.32万","price":0,"oprice":0,"cprice":0,"per":0,"per0":0,"per1":0,"per2":0,"per3":0,"per4":0,"per5":0,"per6":0,"per7":0,"per8":0,"per9":0,"per10":0,"per11":0},{"date":"2025-03-13","name":"科信技术","code":"300565","remark":"净买: 3072.79万","price":0,"oprice":0,"cprice":0,"per":0,"per0":0,"per1":0,"per2":0,"per3":0,"per4":0,"per5":0,"per6":0,"per7":0,"per8":0,"per9":0,"per10":0,"per11":0},{"date":"2025-03-14","name":"信隆健康","code":"002105","remark":"净买: 910.51万","price":0,"oprice":0,"cprice":0,"per":0,"per0":0,"per1":0,"per2":0,"per3":0,"per4":0,"per5":0,"per6":0,"per7":0,"per8":0,"per9":0,"per10":0,"per11":0},{"date":"2025-03-14","name":"志晟信息","code":"832171","remark":"净买: 1424.10万","price":0,"oprice":0,"cprice":0,"per":0,"per0":0,"per1":0,"per2":0,"per3":0,"per4":0,"per5":0,"per6":0,"per7":0,"per8":0,"per9":0,"per10":0,"per11":0},{"date":"2025-03-14","name":"无锡晶海","code":"836547","remark":"净买: 1397.62万","price":0,"oprice":0,"cprice":0,"per":0,"per0":0,"per1":0,"per2":0,"per3":0,"per4":0,"per5":0,"per6":0,"per7":0,"per8":0,"per9":0,"per10":0,"per11":0},{"date":"2025-03-14","name":"美心翼申","code":"873833","remark":"净买: 735.77万","price":0,"oprice":0,"cprice":0,"per":0,"per0":0,"per1":0,"per2":0,"per3":0,"per4":0,"per5":0,"per6":0,"per7":0,"per8":0,"per9":0,"per10":0,"per11":0},{"date":"2025-03-14","name":"狮头股份","code":"600539","remark":"净卖: -1076.17万","price":0,"oprice":0,"cprice":0,"per":0,"per0":0,"per1":0,"per2":0,"per3":0,"per4":0,"per5":0,"per6":0,"per7":0,"per8":0,"per9":0,"per10":0,"per11":0},{"date":"2025-03-17","name":"美心翼申","code":"873833","remark":"净卖: -538.85万","price":0,"oprice":0,"cprice":0,"per":0,"per0":0,"per1":0,"per2":0,"per3":0,"per4":0,"per5":0,"per6":0,"per7":0,"per8":0,"per9":0,"per10":0,"per11":0},{"date":"2025-03-17","name":"信隆健康","code":"002105","remark":"净买: 597.23万","price":0,"oprice":0,"cprice":0,"per":0,"per0":0,"per1":0,"per2":0,"per3":0,"per4":0,"per5":0,"per6":0,"per7":0,"per8":0,"per9":0,"per10":0,"per11":0},{"date":"2025-03-17","name":"金逸影视","code":"002905","remark":"净买: 1157.45万","price":0,"oprice":0,"cprice":0,"per":0,"per0":0,"per1":0,"per2":0,"per3":0,"per4":0,"per5":0,"per6":0,"per7":0,"per8":0,"per9":0,"per10":0,"per11":0},{"date":"2025-03-18","name":"信隆健康","code":"002105","remark":"净卖: -1854.49万","price":0,"oprice":0,"cprice":0,"per":0,"per0":0,"per1":0,"per2":0,"per3":0,"per4":0,"per5":0,"per6":0,"per7":0,"per8":0,"per9":0,"per10":0,"per11":0},{"date":"2025-03-18","name":"金逸影视","code":"002905","remark":"净卖: -1076.41万","price":0,"oprice":0,"cprice":0,"per":0,"per0":0,"per1":0,"per2":0,"per3":0,"per4":0,"per5":0,"per6":0,"per7":0,"per8":0,"per9":0,"per10":0,"per11":0},{"date":"2025-03-19","name":"国脉科技","code":"002093","remark":"净买: 5710.02万","price":0,"oprice":0,"cprice":0,"per":0,"per0":0,"per1":0,"per2":0,"per3":0,"per4":0,"per5":0,"per6":0,"per7":0,"per8":0,"per9":0,"per10":0,"per11":0},{"date":"2025-03-19","name":"泰永长征","code":"002927","remark":"净买: 1093.29万","price":0,"oprice":0,"cprice":0,"per":0,"per0":0,"per1":0,"per2":0,"per3":0,"per4":0,"per5":0,"per6":0,"per7":0,"per8":0,"per9":0,"per10":0,"per11":0},{"date":"2025-03-19","name":"襄阳轴承","code":"000678","remark":"净卖: -127.63万","price":0,"oprice":0,"cprice":0,"per":0,"per0":0,"per1":0,"per2":0,"per3":0,"per4":0,"per5":0,"per6":0,"per7":0,"per8":0,"per9":0,"per10":0,"per11":0},{"date":"2025-03-20","name":"奇精机械","code":"603677","remark":"净卖: -1545.46万","price":0,"oprice":0,"cprice":0,"per":0,"per0":0,"per1":0,"per2":0,"per3":0,"per4":0,"per5":0,"per6":0,"per7":0,"per8":0,"per9":0,"per10":0,"per11":0},{"date":"2025-03-20","name":"襄阳轴承","code":"000678","remark":"净卖: -1966.92万","price":0,"oprice":0,"cprice":0,"per":0,"per0":0,"per1":0,"per2":0,"per3":0,"per4":0,"per5":0,"per6":0,"per7":0,"per8":0,"per9":0,"per10":0,"per11":0},{"date":"2025-03-21","name":"泰永长征","code":"002927","remark":"净卖: -1288.82万","price":0,"oprice":0,"cprice":0,"per":0,"per0":0,"per1":0,"per2":0,"per3":0,"per4":0,"per5":0,"per6":0,"per7":0,"per8":0,"per9":0,"per10":0,"per11":0},{"date":"2025-03-21","name":"克莱特","code":"831689","remark":"净买: 777.51万","price":0,"oprice":0,"cprice":0,"per":0,"per0":0,"per1":0,"per2":0,"per3":0,"per4":0,"per5":0,"per6":0,"per7":0,"per8":0,"per9":0,"per10":0,"per11":0},{"date":"2025-03-21","name":"力鼎光电","code":"605118","remark":"净卖: -1072.92万","price":0,"oprice":0,"cprice":0,"per":0,"per0":0,"per1":0,"per2":0,"per3":0,"per4":0,"per5":0,"per6":0,"per7":0,"per8":0,"per9":0,"per10":0,"per11":0},{"date":"2025-03-21","name":"神州信息","code":"000555","remark":"净买: 4841.03万","price":0,"oprice":0,"cprice":0,"per":0,"per0":0,"per1":0,"per2":0,"per3":0,"per4":0,"per5":0,"per6":0,"per7":0,"per8":0,"per9":0,"per10":0,"per11":0},{"date":"2025-03-25","name":"王子新材","code":"002735","remark":"净买: 2803.85万","price":0,"oprice":0,"cprice":0,"per":0,"per0":0,"per1":0,"per2":0,"per3":0,"per4":0,"per5":0,"per6":0,"per7":0,"per8":0,"per9":0,"per10":0,"per11":0},{"date":"2025-03-25","name":"正和生态","code":"605069","remark":"净买: 953.88万","price":0,"oprice":0,"cprice":0,"per":0,"per0":0,"per1":0,"per2":0,"per3":0,"per4":0,"per5":0,"per6":0,"per7":0,"per8":0,"per9":0,"per10":0,"per11":0},{"date":"2025-03-25","name":"神州信息","code":"000555","remark":"净卖: -3146.23万","price":0,"oprice":0,"cprice":0,"per":0,"per0":0,"per1":0,"per2":0,"per3":0,"per4":0,"per5":0,"per6":0,"per7":0,"per8":0,"per9":0,"per10":0,"per11":0},{"date":"2025-03-26","name":"神州信息","code":"000555","remark":"净卖: -3934.29万","price":0,"oprice":0,"cprice":0,"per":0,"per0":0,"per1":0,"per2":0,"per3":0,"per4":0,"per5":0,"per6":0,"per7":0,"per8":0,"per9":0,"per10":0,"per11":0},{"date":"2025-03-26","name":"王子新材","code":"002735","remark":"净卖: -2416.55万","price":0,"oprice":0,"cprice":0,"per":0,"per0":0,"per1":0,"per2":0,"per3":0,"per4":0,"per5":0,"per6":0,"per7":0,"per8":0,"per9":0,"per10":0,"per11":0},{"date":"2025-03-27","name":"福达合金","code":"603045","remark":"净卖: -2977.93万","price":0,"oprice":0,"cprice":0,"per":0,"per0":0,"per1":0,"per2":0,"per3":0,"per4":0,"per5":0,"per6":0,"per7":0,"per8":0,"per9":0,"per10":0,"per11":0},{"date":"2025-03-28","name":"合金投资","code":"000633","remark":"净买: 403.20万","price":0,"oprice":0,"cprice":0,"per":0,"per0":0,"per1":0,"per2":0,"per3":0,"per4":0,"per5":0,"per6":0,"per7":0,"per8":0,"per9":0,"per10":0,"per11":0},{"date":"2025-03-31","name":"新铝时代","code":"301613","remark":"净买: 1370.07万","price":0,"oprice":0,"cprice":0,"per":0,"per0":0,"per1":0,"per2":0,"per3":0,"per4":0,"per5":0,"per6":0,"per7":0,"per8":0,"per9":0,"per10":0,"per11":0},{"date":"2025-03-31","name":"润都股份","code":"002923","remark":"净卖: -1619.02万","price":0,"oprice":0,"cprice":0,"per":0,"per0":0,"per1":0,"per2":0,"per3":0,"per4":0,"per5":0,"per6":0,"per7":0,"per8":0,"per9":0,"per10":0,"per11":0},{"date":"2025-04-01","name":"多瑞医药","code":"301075","remark":"净买: 2166.43万","price":0,"oprice":0,"cprice":0,"per":0,"per0":0,"per1":0,"per2":0,"per3":0,"per4":0,"per5":0,"per6":0,"per7":0,"per8":0,"per9":0,"per10":0,"per11":0},{"date":"2025-04-01","name":"河化股份","code":"000953","remark":"净买: 637.73万","price":0,"oprice":0,"cprice":0,"per":0,"per0":0,"per1":0,"per2":0,"per3":0,"per4":0,"per5":0,"per6":0,"per7":0,"per8":0,"per9":0,"per10":0,"per11":0},{"date":"2025-04-01","name":"楚环科技","code":"001336","remark":"净卖: -92.12万","price":0,"oprice":0,"cprice":0,"per":0,"per0":0,"per1":0,"per2":0,"per3":0,"per4":0,"per5":0,"per6":0,"per7":0,"per8":0,"per9":0,"per10":0,"per11":0},{"date":"2025-04-01","name":"恒兴新材","code":"603276","remark":"净买: 570.75万","price":0,"oprice":0,"cprice":0,"per":0,"per0":0,"per1":0,"per2":0,"per3":0,"per4":0,"per5":0,"per6":0,"per7":0,"per8":0,"per9":0,"per10":0,"per11":0},{"date":"2025-04-02","name":"河化股份","code":"000953","remark":"净卖: -895.77万","price":0,"oprice":0,"cprice":0,"per":0,"per0":0,"per1":0,"per2":0,"per3":0,"per4":0,"per5":0,"per6":0,"per7":0,"per8":0,"per9":0,"per10":0,"per11":0},{"date":"2025-04-03","name":"岭南控股","code":"000524","remark":"净买: 265.46万","price":0,"oprice":0,"cprice":0,"per":0,"per0":0,"per1":0,"per2":0,"per3":0,"per4":0,"per5":0,"per6":0,"per7":0,"per8":0,"per9":0,"per10":0,"per11":0},{"date":"2025-04-03","name":"迪生力","code":"603335","remark":"净买: 600.65万","price":0,"oprice":0,"cprice":0,"per":0,"per0":0,"per1":0,"per2":0,"per3":0,"per4":0,"per5":0,"per6":0,"per7":0,"per8":0,"per9":0,"per10":0,"per11":0},{"date":"2025-04-03","name":"美农生物","code":"301156","remark":"净买: 962.44万","price":0,"oprice":0,"cprice":0,"per":0,"per0":0,"per1":0,"per2":0,"per3":0,"per4":0,"per5":0,"per6":0,"per7":0,"per8":0,"per9":0,"per10":0,"per11":0},{"date":"2025-04-07","name":"哈三联","code":"002900","remark":"净买: 1920.21万","price":0,"oprice":0,"cprice":0,"per":0,"per0":0,"per1":0,"per2":0,"per3":0,"per4":0,"per5":0,"per6":0,"per7":0,"per8":0,"per9":0,"per10":0,"per11":0},{"date":"2025-04-07","name":"美农生物","code":"301156","remark":"净买: 1988.24万","price":0,"oprice":0,"cprice":0,"per":0,"per0":0,"per1":0,"per2":0,"per3":0,"per4":0,"per5":0,"per6":0,"per7":0,"per8":0,"per9":0,"per10":0,"per11":0},{"date":"2025-04-07","name":"中创物流","code":"603967","remark":"净买: 2308.62万","price":0,"oprice":0,"cprice":0,"per":0,"per0":0,"per1":0,"per2":0,"per3":0,"per4":0,"per5":0,"per6":0,"per7":0,"per8":0,"per9":0,"per10":0,"per11":0},{"date":"2025-04-07","name":"湘佳股份","code":"002982","remark":"净买: 1569.24万","price":0,"oprice":0,"cprice":0,"per":0,"per0":0,"per1":0,"per2":0,"per3":0,"per4":0,"per5":0,"per6":0,"per7":0,"per8":0,"per9":0,"per10":0,"per11":0},{"date":"2025-04-07","name":"晓鸣股份","code":"300967","remark":"净买: 1041.31万","price":0,"oprice":0,"cprice":0,"per":0,"per0":0,"per1":0,"per2":0,"per3":0,"per4":0,"per5":0,"per6":0,"per7":0,"per8":0,"per9":0,"per10":0,"per11":0},{"date":"2025-04-07","name":"祖名股份","code":"003030","remark":"净买: 35.03万","price":0,"oprice":0,"cprice":0,"per":0,"per0":0,"per1":0,"per2":0,"per3":0,"per4":0,"per5":0,"per6":0,"per7":0,"per8":0,"per9":0,"per10":0,"per11":0},{"date":"2025-04-08","name":"祖名股份","code":"003030","remark":"净卖: -1232.63万","price":0,"oprice":0,"cprice":0,"per":0,"per0":0,"per1":0,"per2":0,"per3":0,"per4":0,"per5":0,"per6":0,"per7":0,"per8":0,"per9":0,"per10":0,"per11":0},{"date":"2025-04-08","name":"美农生物","code":"301156","remark":"净卖: -2540.03万","price":0,"oprice":0,"cprice":0,"per":0,"per0":0,"per1":0,"per2":0,"per3":0,"per4":0,"per5":0,"per6":0,"per7":0,"per8":0,"per9":0,"per10":0,"per11":0},{"date":"2025-04-08","name":"中创物流","code":"603967","remark":"净卖: -2227.55万","price":0,"oprice":0,"cprice":0,"per":0,"per0":0,"per1":0,"per2":0,"per3":0,"per4":0,"per5":0,"per6":0,"per7":0,"per8":0,"per9":0,"per10":0,"per11":0},{"date":"2025-04-08","name":"晓鸣股份","code":"300967","remark":"净卖: -1057.72万","price":0,"oprice":0,"cprice":0,"per":0,"per0":0,"per1":0,"per2":0,"per3":0,"per4":0,"per5":0,"per6":0,"per7":0,"per8":0,"per9":0,"per10":0,"per11":0},{"date":"2025-04-08","name":"哈三联","code":"002900","remark":"净卖: -1702.29万","price":0,"oprice":0,"cprice":0,"per":0,"per0":0,"per1":0,"per2":0,"per3":0,"per4":0,"per5":0,"per6":0,"per7":0,"per8":0,"per9":0,"per10":0,"per11":0},{"date":"2025-04-09","name":"飞力达","code":"300240","remark":"净买: 2328.00万","price":0,"oprice":0,"cprice":0,"per":0,"per0":0,"per1":0,"per2":0,"per3":0,"per4":0,"per5":0,"per6":0,"per7":0,"per8":0,"per9":0,"per10":0,"per11":0},{"date":"2025-04-09","name":"美农生物","code":"301156","remark":"净卖: -3604.01万","price":0,"oprice":0,"cprice":0,"per":0,"per0":0,"per1":0,"per2":0,"per3":0,"per4":0,"per5":0,"per6":0,"per7":0,"per8":0,"per9":0,"per10":0,"per11":0},{"date":"2025-04-09","name":"瑞茂通","code":"600180","remark":"净买: 1346.43万","price":0,"oprice":0,"cprice":0,"per":0,"per0":0,"per1":0,"per2":0,"per3":0,"per4":0,"per5":0,"per6":0,"per7":0,"per8":0,"per9":0,"per10":0,"per11":0},{"date":"2025-04-09","name":"祖名股份","code":"003030","remark":"净卖: -566.61万","price":0,"oprice":0,"cprice":0,"per":0,"per0":0,"per1":0,"per2":0,"per3":0,"per4":0,"per5":0,"per6":0,"per7":0,"per8":0,"per9":0,"per10":0,"per11":0},{"date":"2025-04-09","name":"品渥食品","code":"300892","remark":"净买: 829.26万","price":0,"oprice":0,"cprice":0,"per":0,"per0":0,"per1":0,"per2":0,"per3":0,"per4":0,"per5":0,"per6":0,"per7":0,"per8":0,"per9":0,"per10":0,"per11":0},{"date":"2025-04-10","name":"国芳集团","code":"601086","remark":"净卖: -1053.31万","price":0,"oprice":0,"cprice":0,"per":0,"per0":0,"per1":0,"per2":0,"per3":0,"per4":0,"per5":0,"per6":0,"per7":0,"per8":0,"per9":0,"per10":0,"per11":0},{"date":"2025-04-10","name":"海鸥住工","code":"002084","remark":"净买: 650.70万","price":0,"oprice":0,"cprice":0,"per":0,"per0":0,"per1":0,"per2":0,"per3":0,"per4":0,"per5":0,"per6":0,"per7":0,"per8":0,"per9":0,"per10":0,"per11":0},{"date":"2025-04-10","name":"飞力达","code":"300240","remark":"净卖: -491.58万","price":0,"oprice":0,"cprice":0,"per":0,"per0":0,"per1":0,"per2":0,"per3":0,"per4":0,"per5":0,"per6":0,"per7":0,"per8":0,"per9":0,"per10":0,"per11":0},{"date":"2025-04-11","name":"深圳华强","code":"000062","remark":"净买: 2215.70万","price":0,"oprice":0,"cprice":0,"per":0,"per0":0,"per1":0,"per2":0,"per3":0,"per4":0,"per5":0,"per6":0,"per7":0,"per8":0,"per9":0,"per10":0,"per11":0},{"date":"2025-04-11","name":"海鸥住工","code":"002084","remark":"净卖: -1017.84万","price":0,"oprice":0,"cprice":0,"per":0,"per0":0,"per1":0,"per2":0,"per3":0,"per4":0,"per5":0,"per6":0,"per7":0,"per8":0,"per9":0,"per10":0,"per11":0},{"date":"2025-04-11","name":"飞力达","code":"300240","remark":"净卖: -2139.39万","price":0,"oprice":0,"cprice":0,"per":0,"per0":0,"per1":0,"per2":0,"per3":0,"per4":0,"per5":0,"per6":0,"per7":0,"per8":0,"per9":0,"per10":0,"per11":0},{"date":"2025-04-11","name":"民德电子","code":"300656","remark":"净买: 984.47万","price":0,"oprice":0,"cprice":0,"per":0,"per0":0,"per1":0,"per2":0,"per3":0,"per4":0,"per5":0,"per6":0,"per7":0,"per8":0,"per9":0,"per10":0,"per11":0},{"date":"2025-04-14","name":"深圳华强","code":"000062","remark":"净卖: -2249.01万","price":0,"oprice":0,"cprice":0,"per":0,"per0":0,"per1":0,"per2":0,"per3":0,"per4":0,"per5":0,"per6":0,"per7":0,"per8":0,"per9":0,"per10":0,"per11":0},{"date":"2025-04-14","name":"和科达","code":"002816","remark":"净卖: -11.65万","price":0,"oprice":0,"cprice":0,"per":0,"per0":0,"per1":0,"per2":0,"per3":0,"per4":0,"per5":0,"per6":0,"per7":0,"per8":0,"per9":0,"per10":0,"per11":0},{"date":"2025-04-14","name":"通达创智","code":"001368","remark":"净买: 501.85万","price":0,"oprice":0,"cprice":0,"per":0,"per0":0,"per1":0,"per2":0,"per3":0,"per4":0,"per5":0,"per6":0,"per7":0,"per8":0,"per9":0,"per10":0,"per11":0},{"date":"2025-04-14","name":"海南海药","code":"000566","remark":"净买: 1367.47万","price":0,"oprice":0,"cprice":0,"per":0,"per0":0,"per1":0,"per2":0,"per3":0,"per4":0,"per5":0,"per6":0,"per7":0,"per8":0,"per9":0,"per10":0,"per11":0},{"date":"2025-04-15","name":"汇鸿集团","code":"600981","remark":"净卖: -443.04万","price":0,"oprice":0,"cprice":0,"per":0,"per0":0,"per1":0,"per2":0,"per3":0,"per4":0,"per5":0,"per6":0,"per7":0,"per8":0,"per9":0,"per10":0,"per11":0},{"date":"2025-04-15","name":"久祺股份","code":"300994","remark":"净买: 1214.03万","price":0,"oprice":0,"cprice":0,"per":0,"per0":0,"per1":0,"per2":0,"per3":0,"per4":0,"per5":0,"per6":0,"per7":0,"per8":0,"per9":0,"per10":0,"per11":0},{"date":"2025-04-16","name":"麦趣尔","code":"002719","remark":"净买: 1297.56万","price":0,"oprice":0,"cprice":0,"per":0,"per0":0,"per1":0,"per2":0,"per3":0,"per4":0,"per5":0,"per6":0,"per7":0,"per8":0,"per9":0,"per10":0,"per11":0},{"date":"2025-04-16","name":"中创物流","code":"603967","remark":"净买: 1250.98万","price":0,"oprice":0,"cprice":0,"per":0,"per0":0,"per1":0,"per2":0,"per3":0,"per4":0,"per5":0,"per6":0,"per7":0,"per8":0,"per9":0,"per10":0,"per11":0},{"date":"2025-04-17","name":"麦趣尔","code":"002719","remark":"净卖: -1096.35万","price":0,"oprice":0,"cprice":0,"per":0,"per0":0,"per1":0,"per2":0,"per3":0,"per4":0,"per5":0,"per6":0,"per7":0,"per8":0,"per9":0,"per10":0,"per11":0},{"date":"2025-04-17","name":"一鸣食品","code":"605179","remark":"净买: 1082.94万","price":0,"oprice":0,"cprice":0,"per":0,"per0":0,"per1":0,"per2":0,"per3":0,"per4":0,"per5":0,"per6":0,"per7":0,"per8":0,"per9":0,"per10":0,"per11":0},{"date":"2025-04-17","name":"荣丰控股","code":"000668","remark":"净买: 407.72万","price":0,"oprice":0,"cprice":0,"per":0,"per0":0,"per1":0,"per2":0,"per3":0,"per4":0,"per5":0,"per6":0,"per7":0,"per8":0,"per9":0,"per10":0,"per11":0},{"date":"2025-04-18","name":"宏昌电子","code":"603002","remark":"净买: 1983.89万","price":0,"oprice":0,"cprice":0,"per":0,"per0":0,"per1":0,"per2":0,"per3":0,"per4":0,"per5":0,"per6":0,"per7":0,"per8":0,"per9":0,"per10":0,"per11":0},{"date":"2025-04-18","name":"天沃科技","code":"002564","remark":"净买: 1593.46万","price":0,"oprice":0,"cprice":0,"per":0,"per0":0,"per1":0,"per2":0,"per3":0,"per4":0,"per5":0,"per6":0,"per7":0,"per8":0,"per9":0,"per10":0,"per11":0},{"date":"2025-04-18","name":"泰慕士","code":"001234","remark":"净卖: -1017.51万","price":0,"oprice":0,"cprice":0,"per":0,"per0":0,"per1":0,"per2":0,"per3":0,"per4":0,"per5":0,"per6":0,"per7":0,"per8":0,"per9":0,"per10":0,"per11":0},{"date":"2025-04-21","name":"国光连锁","code":"605188","remark":"净买: 1246.29万","price":0,"oprice":0,"cprice":0,"per":0,"per0":0,"per1":0,"per2":0,"per3":0,"per4":0,"per5":0,"per6":0,"per7":0,"per8":0,"per9":0,"per10":0,"per11":0},{"date":"2025-04-21","name":"泰慕士","code":"001234","remark":"净卖: -1010.10万","price":0,"oprice":0,"cprice":0,"per":0,"per0":0,"per1":0,"per2":0,"per3":0,"per4":0,"per5":0,"per6":0,"per7":0,"per8":0,"per9":0,"per10":0,"per11":0},{"date":"2025-04-22","name":"凯美特气","code":"002549","remark":"净买: 1545.53万","price":0,"oprice":0,"cprice":0,"per":0,"per0":0,"per1":0,"per2":0,"per3":0,"per4":0,"per5":0,"per6":0,"per7":0,"per8":0,"per9":0,"per10":0,"per11":0},{"date":"2025-04-22","name":"中毅达","code":"600610","remark":"净卖: -1256.30万","price":0,"oprice":0,"cprice":0,"per":0,"per0":0,"per1":0,"per2":0,"per3":0,"per4":0,"per5":0,"per6":0,"per7":0,"per8":0,"per9":0,"per10":0,"per11":0},{"date":"2025-04-22","name":"国光连锁","code":"605188","remark":"净卖: -1149.48万","price":0,"oprice":0,"cprice":0,"per":0,"per0":0,"per1":0,"per2":0,"per3":0,"per4":0,"per5":0,"per6":0,"per7":0,"per8":0,"per9":0,"per10":0,"per11":0},{"date":"2025-04-23","name":"轻纺城","code":"600790","remark":"净买: 3512.30万","price":0,"oprice":0,"cprice":0,"per":0,"per0":0,"per1":0,"per2":0,"per3":0,"per4":0,"per5":0,"per6":0,"per7":0,"per8":0,"per9":0,"per10":0,"per11":0},{"date":"2025-04-24","name":"轻纺城","code":"600790","remark":"净卖: -3397.03万","price":0,"oprice":0,"cprice":0,"per":0,"per0":0,"per1":0,"per2":0,"per3":0,"per4":0,"per5":0,"per6":0,"per7":0,"per8":0,"per9":0,"per10":0,"per11":0},{"date":"2025-04-24","name":"科拜尔","code":"920066","remark":"净卖: -431.66万","price":0,"oprice":0,"cprice":0,"per":0,"per0":0,"per1":0,"per2":0,"per3":0,"per4":0,"per5":0,"per6":0,"per7":0,"per8":0,"per9":0,"per10":0,"per11":0},{"date":"2025-04-24","name":"嘉诚国际","code":"603535","remark":"净卖: -1816.53万","price":0,"oprice":0,"cprice":0,"per":0,"per0":0,"per1":0,"per2":0,"per3":0,"per4":0,"per5":0,"per6":0,"per7":0,"per8":0,"per9":0,"per10":0,"per11":0},{"date":"2025-04-24","name":"健尔康","code":"603205","remark":"净买: 1512.62万","price":0,"oprice":0,"cprice":0,"per":0,"per0":0,"per1":0,"per2":0,"per3":0,"per4":0,"per5":0,"per6":0,"per7":0,"per8":0,"per9":0,"per10":0,"per11":0},{"date":"2025-04-24","name":"尔康制药","code":"300267","remark":"净买: 1462.75万","price":0,"oprice":0,"cprice":0,"per":0,"per0":0,"per1":0,"per2":0,"per3":0,"per4":0,"per5":0,"per6":0,"per7":0,"per8":0,"per9":0,"per10":0,"per11":0},{"date":"2025-04-25","name":"永安药业","code":"002365","remark":"净卖: -1408.52万","price":0,"oprice":0,"cprice":0,"per":0,"per0":0,"per1":0,"per2":0,"per3":0,"per4":0,"per5":0,"per6":0,"per7":0,"per8":0,"per9":0,"per10":0,"per11":0},{"date":"2025-04-25","name":"宁波联合","code":"600051","remark":"净买: 1686.55万","price":0,"oprice":0,"cprice":0,"per":0,"per0":0,"per1":0,"per2":0,"per3":0,"per4":0,"per5":0,"per6":0,"per7":0,"per8":0,"per9":0,"per10":0,"per11":0},{"date":"2025-04-25","name":"健尔康","code":"603205","remark":"净卖: -1498.52万","price":0,"oprice":0,"cprice":0,"per":0,"per0":0,"per1":0,"per2":0,"per3":0,"per4":0,"per5":0,"per6":0,"per7":0,"per8":0,"per9":0,"per10":0,"per11":0},{"date":"2025-04-25","name":"和展能源","code":"000809","remark":"净买: 817.39万","price":0,"oprice":0,"cprice":0,"per":0,"per0":0,"per1":0,"per2":0,"per3":0,"per4":0,"per5":0,"per6":0,"per7":0,"per8":0,"per9":0,"per10":0,"per11":0},{"date":"2025-04-28","name":"宁波联合","code":"600051","remark":"净卖: -1995.83万","price":0,"oprice":0,"cprice":0,"per":0,"per0":0,"per1":0,"per2":0,"per3":0,"per4":0,"per5":0,"per6":0,"per7":0,"per8":0,"per9":0,"per10":0,"per11":0},{"date":"2025-04-28","name":"渝三峡A","code":"000565","remark":"净买: 1166.39万","price":0,"oprice":0,"cprice":0,"per":0,"per0":0,"per1":0,"per2":0,"per3":0,"per4":0,"per5":0,"per6":0,"per7":0,"per8":0,"per9":0,"per10":0,"per11":0},{"date":"2025-04-28","name":"浔兴股份","code":"002098","remark":"净卖: -1112.15万","price":0,"oprice":0,"cprice":0,"per":0,"per0":0,"per1":0,"per2":0,"per3":0,"per4":0,"per5":0,"per6":0,"per7":0,"per8":0,"per9":0,"per10":0,"per11":0},{"date":"2025-04-28","name":"德生科技","code":"002908","remark":"净买: 1124.54万","price":0,"oprice":0,"cprice":0,"per":0,"per0":0,"per1":0,"per2":0,"per3":0,"per4":0,"per5":0,"per6":0,"per7":0,"per8":0,"per9":0,"per10":0,"per11":0},{"date":"2025-04-29","name":"新瀚新材","code":"301076","remark":"净买: 1846.36万","price":0,"oprice":0,"cprice":0,"per":0,"per0":0,"per1":0,"per2":0,"per3":0,"per4":0,"per5":0,"per6":0,"per7":0,"per8":0,"per9":0,"per10":0,"per11":0},{"date":"2025-04-29","name":"安记食品","code":"603696","remark":"净买: 1422.08万","price":0,"oprice":0,"cprice":0,"per":0,"per0":0,"per1":0,"per2":0,"per3":0,"per4":0,"per5":0,"per6":0,"per7":0,"per8":0,"per9":0,"per10":0,"per11":0},{"date":"2025-04-29","name":"联合化学","code":"301209","remark":"净买: 1882.46万","price":0,"oprice":0,"cprice":0,"per":0,"per0":0,"per1":0,"per2":0,"per3":0,"per4":0,"per5":0,"per6":0,"per7":0,"per8":0,"per9":0,"per10":0,"per11":0},{"date":"2025-04-30","name":"中旗新材","code":"001212","remark":"净卖: -2303.75万","price":0,"oprice":0,"cprice":0,"per":0,"per0":0,"per1":0,"per2":0,"per3":0,"per4":0,"per5":0,"per6":0,"per7":0,"per8":0,"per9":0,"per10":0,"per11":0},{"date":"2025-04-30","name":"新瀚新材","code":"301076","remark":"净卖: -1694.47万","price":0,"oprice":0,"cprice":0,"per":0,"per0":0,"per1":0,"per2":0,"per3":0,"per4":0,"per5":0,"per6":0,"per7":0,"per8":0,"per9":0,"per10":0,"per11":0},{"date":"2025-04-30","name":"渝三峡A","code":"000565","remark":"净卖: -1311.39万","price":0,"oprice":0,"cprice":0,"per":0,"per0":0,"per1":0,"per2":0,"per3":0,"per4":0,"per5":0,"per6":0,"per7":0,"per8":0,"per9":0,"per10":0,"per11":0},{"date":"2025-05-06","name":"东珠生态","code":"603359","remark":"净买: 1502.24万","price":0,"oprice":0,"cprice":0,"per":0,"per0":0,"per1":0,"per2":0,"per3":0,"per4":0,"per5":0,"per6":0,"per7":0,"per8":0,"per9":0,"per10":0,"per11":0},{"date":"2025-05-06","name":"安记食品","code":"603696","remark":"净卖: -908.56万","price":0,"oprice":0,"cprice":0,"per":0,"per0":0,"per1":0,"per2":0,"per3":0,"per4":0,"per5":0,"per6":0,"per7":0,"per8":0,"per9":0,"per10":0,"per11":0},{"date":"2025-05-06","name":"华阳新材","code":"600281","remark":"净买: 1458.27万","price":0,"oprice":0,"cprice":0,"per":0,"per0":0,"per1":0,"per2":0,"per3":0,"per4":0,"per5":0,"per6":0,"per7":0,"per8":0,"per9":0,"per10":0,"per11":0},{"date":"2025-05-07","name":"华阳新材","code":"600281","remark":"净买: 2.79万","price":0,"oprice":0,"cprice":0,"per":0,"per0":0,"per1":0,"per2":0,"per3":0,"per4":0,"per5":0,"per6":0,"per7":0,"per8":0,"per9":0,"per10":0,"per11":0},{"date":"2025-05-07","name":"东珠生态","code":"603359","remark":"净卖: -1189.95万","price":0,"oprice":0,"cprice":0,"per":0,"per0":0,"per1":0,"per2":0,"per3":0,"per4":0,"per5":0,"per6":0,"per7":0,"per8":0,"per9":0,"per10":0,"per11":0},{"date":"2025-05-08","name":"全筑股份","code":"603030","remark":"净卖: -1487.71万","price":0,"oprice":0,"cprice":0,"per":0,"per0":0,"per1":0,"per2":0,"per3":0,"per4":0,"per5":0,"per6":0,"per7":0,"per8":0,"per9":0,"per10":0,"per11":0},{"date":"2025-05-09","name":"百达精工","code":"603331","remark":"净买: 551.10万","price":0,"oprice":0,"cprice":0,"per":0,"per0":0,"per1":0,"per2":0,"per3":0,"per4":0,"per5":0,"per6":0,"per7":0,"per8":0,"per9":0,"per10":0,"per11":0},{"date":"2025-05-12","name":"宏达高科","code":"002144","remark":"净买: 1970.42万","price":0,"oprice":0,"cprice":0,"per":0,"per0":0,"per1":0,"per2":0,"per3":0,"per4":0,"per5":0,"per6":0,"per7":0,"per8":0,"per9":0,"per10":0,"per11":0},{"date":"2025-05-12","name":"百达精工","code":"603331","remark":"净卖: -651.66万","price":0,"oprice":0,"cprice":0,"per":0,"per0":0,"per1":0,"per2":0,"per3":0,"per4":0,"per5":0,"per6":0,"per7":0,"per8":0,"per9":0,"per10":0,"per11":0},{"date":"2025-05-19","name":"五新隧装","code":"835174","remark":"净买: 686.16万","price":0,"oprice":0,"cprice":0,"per":0,"per0":0,"per1":0,"per2":0,"per3":0,"per4":0,"per5":0,"per6":0,"per7":0,"per8":0,"per9":0,"per10":0,"per11":0},{"date":"2025-06-05","name":"中旗新材","code":"001212","remark":"净买: 189.17万","price":0,"oprice":0,"cprice":0,"per":0,"per0":0,"per1":0,"per2":0,"per3":0,"per4":0,"per5":0,"per6":0,"per7":0,"per8":0,"per9":0,"per10":0,"per11":0},{"date":"2025-06-11","name":"永安药业","code":"002365","remark":"净卖: -1013.68万","price":0,"oprice":0,"cprice":0,"per":0,"per0":0,"per1":0,"per2":0,"per3":0,"per4":0,"per5":0,"per6":0,"per7":0,"per8":0,"per9":0,"per10":0,"per11":0},{"date":"2025-06-30","name":"翔宇医疗","code":"688626","remark":"净卖: -782.06万","price":0,"oprice":0,"cprice":0,"per":0,"per0":0,"per1":0,"per2":0,"per3":0,"per4":0,"per5":0,"per6":0,"per7":0,"per8":0,"per9":0,"per10":0,"per11":0},{"date":"2025-08-04","name":"山河智能","code":"002097","remark":"净买: 3956.55万","price":0,"oprice":0,"cprice":0,"per":0,"per0":0,"per1":0,"per2":0,"per3":0,"per4":0,"per5":0,"per6":0,"per7":0,"per8":0,"per9":0,"per10":0,"per11":0},{"date":"2025-08-20","name":"科森科技","code":"603626","remark":"净买: 1048.02万","price":0,"oprice":0,"cprice":0,"per":0,"per0":0,"per1":0,"per2":0,"per3":0,"per4":0,"per5":0,"per6":0,"per7":0,"per8":0,"per9":0,"per10":0,"per11":0},{"date":"2025-09-05","name":"济民健康","code":"603222","remark":"净买: 958.78万","price":0,"oprice":0,"cprice":0,"per":0,"per0":0,"per1":0,"per2":0,"per3":0,"per4":0,"per5":0,"per6":0,"per7":0,"per8":0,"per9":0,"per10":0,"per11":0},{"date":"2025-09-12","name":"中国瑞林","code":"603257","remark":"净买: 356.98万","price":0,"oprice":0,"cprice":0,"per":0,"per0":0,"per1":0,"per2":0,"per3":0,"per4":0,"per5":0,"per6":0,"per7":0,"per8":0,"per9":0,"per10":0,"per11":0},{"date":"2025-09-17","name":"东珠生态","code":"603359","remark":"净卖: -1371.56万","price":0,"oprice":0,"cprice":0,"per":0,"per0":0,"per1":0,"per2":0,"per3":0,"per4":0,"per5":0,"per6":0,"per7":0,"per8":0,"per9":0,"per10":0,"per11":0},{"date":"2025-09-18","name":"中电电机","code":"603988","remark":"净买: 2917.33万","price":0,"oprice":0,"cprice":0,"per":0,"per0":0,"per1":0,"per2":0,"per3":0,"per4":0,"per5":0,"per6":0,"per7":0,"per8":0,"per9":0,"per10":0,"per11":0},{"date":"2025-09-19","name":"建元信托","code":"600816","remark":"净买: 1786.30万","price":0,"oprice":0,"cprice":0,"per":0,"per0":0,"per1":0,"per2":0,"per3":0,"per4":0,"per5":0,"per6":0,"per7":0,"per8":0,"per9":0,"per10":0,"per11":0},{"date":"2025-09-23","name":"鼎信通讯","code":"603421","remark":"净买: 950.81万","price":0,"oprice":0,"cprice":0,"per":0,"per0":0,"per1":0,"per2":0,"per3":0,"per4":0,"per5":0,"per6":0,"per7":0,"per8":0,"per9":0,"per10":0,"per11":0},{"date":"2025-09-24","name":"青山纸业","code":"600103","remark":"净买: 3091.50万","price":0,"oprice":0,"cprice":0,"per":0,"per0":0,"per1":0,"per2":0,"per3":0,"per4":0,"per5":0,"per6":0,"per7":0,"per8":0,"per9":0,"per10":0,"per11":0},{"date":"2025-09-24","name":"兴福电子","code":"688545","remark":"净买: 2055.83万","price":0,"oprice":0,"cprice":0,"per":0,"per0":0,"per1":0,"per2":0,"per3":0,"per4":0,"per5":0,"per6":0,"per7":0,"per8":0,"per9":0,"per10":0,"per11":0},{"date":"2025-09-25","name":"兴福电子","code":"688545","remark":"净卖: -2218.66万","price":0,"oprice":0,"cprice":0,"per":0,"per0":0,"per1":0,"per2":0,"per3":0,"per4":0,"per5":0,"per6":0,"per7":0,"per8":0,"per9":0,"per10":0,"per11":0},{"date":"2025-09-25","name":"青山纸业","code":"600103","remark":"净卖: -3249.13万","price":0,"oprice":0,"cprice":0,"per":0,"per0":0,"per1":0,"per2":0,"per3":0,"per4":0,"per5":0,"per6":0,"per7":0,"per8":0,"per9":0,"per10":0,"per11":0},{"date":"2025-10-10","name":"集友股份","code":"603429","remark":"净卖: -1102.05万","price":0,"oprice":0,"cprice":0,"per":0,"per0":0,"per1":0,"per2":0,"per3":0,"per4":0,"per5":0,"per6":0,"per7":0,"per8":0,"per9":0,"per10":0,"per11":0},{"date":"2025-10-13","name":"宏源药业","code":"301246","remark":"净买: 2292.06万","price":0,"oprice":0,"cprice":0,"per":0,"per0":0,"per1":0,"per2":0,"per3":0,"per4":0,"per5":0,"per6":0,"per7":0,"per8":0,"per9":0,"per10":0,"per11":0},{"date":"2025-10-14","name":"澄星股份","code":"600078","remark":"净买: 996.80万","price":0,"oprice":0,"cprice":0,"per":0,"per0":0,"per1":0,"per2":0,"per3":0,"per4":0,"per5":0,"per6":0,"per7":0,"per8":0,"per9":0,"per10":0,"per11":0},{"date":"2025-10-15","name":"澄星股份","code":"600078","remark":"净买: 3357.90万","price":0,"oprice":0,"cprice":0,"per":0,"per0":0,"per1":0,"per2":0,"per3":0,"per4":0,"per5":0,"per6":0,"per7":0,"per8":0,"per9":0,"per10":0,"per11":0},{"date":"2025-10-15","name":"合肥城建","code":"002208","remark":"净买: 2718.88万","price":0,"oprice":0,"cprice":0,"per":0,"per0":0,"per1":0,"per2":0,"per3":0,"per4":0,"per5":0,"per6":0,"per7":0,"per8":0,"per9":0,"per10":0,"per11":0},{"date":"2025-10-15","name":"安泰科技","code":"000969","remark":"净买: 9413.32万","price":0,"oprice":0,"cprice":0,"per":0,"per0":0,"per1":0,"per2":0,"per3":0,"per4":0,"per5":0,"per6":0,"per7":0,"per8":0,"per9":0,"per10":0,"per11":0},{"date":"2025-10-16","name":"新特电气","code":"301120","remark":"净卖: -2559.89万","price":0,"oprice":0,"cprice":0,"per":0,"per0":0,"per1":0,"per2":0,"per3":0,"per4":0,"per5":0,"per6":0,"per7":0,"per8":0,"per9":0,"per10":0,"per11":0},{"date":"2025-10-17","name":"合肥城建","code":"002208","remark":"净卖: -8492.03万","price":0,"oprice":0,"cprice":0,"per":0,"per0":0,"per1":0,"per2":0,"per3":0,"per4":0,"per5":0,"per6":0,"per7":0,"per8":0,"per9":0,"per10":0,"per11":0},{"date":"2025-10-22","name":"*ST南置","code":"002305","remark":"净买: 806.46万","price":0,"oprice":0,"cprice":0,"per":0,"per0":0,"per1":0,"per2":0,"per3":0,"per4":0,"per5":0,"per6":0,"per7":0,"per8":0,"per9":0,"per10":0,"per11":0},{"date":"2025-10-24","name":"常铝股份","code":"002160","remark":"净买: 2142.75万","price":0,"oprice":0,"cprice":0,"per":0,"per0":0,"per1":0,"per2":0,"per3":0,"per4":0,"per5":0,"per6":0,"per7":0,"per8":0,"per9":0,"per10":0,"per11":0},{"date":"2025-10-27","name":"首开股份","code":"600376","remark":"净卖: -1292.73万","price":0,"oprice":0,"cprice":0,"per":0,"per0":0,"per1":0,"per2":0,"per3":0,"per4":0,"per5":0,"per6":0,"per7":0,"per8":0,"per9":0,"per10":0,"per11":0},{"date":"2025-10-28","name":"海峡创新","code":"300300","remark":"净卖: -1800.68万","price":0,"oprice":0,"cprice":0,"per":0,"per0":0,"per1":0,"per2":0,"per3":0,"per4":0,"per5":0,"per6":0,"per7":0,"per8":0,"per9":0,"per10":0,"per11":0},{"date":"2025-10-28","name":"合肥城建","code":"002208","remark":"净卖: -2711.50万","price":0,"oprice":0,"cprice":0,"per":0,"per0":0,"per1":0,"per2":0,"per3":0,"per4":0,"per5":0,"per6":0,"per7":0,"per8":0,"per9":0,"per10":0,"per11":0},{"date":"2025-10-31","name":"时空科技","code":"605178","remark":"净买: 4334.89万","price":0,"oprice":0,"cprice":0,"per":0,"per0":0,"per1":0,"per2":0,"per3":0,"per4":0,"per5":0,"per6":0,"per7":0,"per8":0,"per9":0,"per10":0,"per11":0},{"date":"2025-11-03","name":"欢瑞世纪","code":"000892","remark":"净买: 1918.12万","price":0,"oprice":0,"cprice":0,"per":0,"per0":0,"per1":0,"per2":0,"per3":0,"per4":0,"per5":0,"per6":0,"per7":0,"per8":0,"per9":0,"per10":0,"per11":0},{"date":"2025-11-03","name":"亚士创能","code":"603378","remark":"净买: 281.67万","price":0,"oprice":0,"cprice":0,"per":0,"per0":0,"per1":0,"per2":0,"per3":0,"per4":0,"per5":0,"per6":0,"per7":0,"per8":0,"per9":0,"per10":0,"per11":0},{"date":"2025-11-04","name":"盈新发展","code":"000620","remark":"净卖: -2525.06万","price":0,"oprice":0,"cprice":0,"per":0,"per0":0,"per1":0,"per2":0,"per3":0,"per4":0,"per5":0,"per6":0,"per7":0,"per8":0,"per9":0,"per10":0,"per11":0},{"date":"2025-11-04","name":"马可波罗","code":"001386","remark":"净买: 1126.10万","price":0,"oprice":0,"cprice":0,"per":0,"per0":0,"per1":0,"per2":0,"per3":0,"per4":0,"per5":0,"per6":0,"per7":0,"per8":0,"per9":0,"per10":0,"per11":0},{"date":"2025-11-04","name":"欢瑞世纪","code":"000892","remark":"净卖: -967.90万","price":0,"oprice":0,"cprice":0,"per":0,"per0":0,"per1":0,"per2":0,"per3":0,"per4":0,"per5":0,"per6":0,"per7":0,"per8":0,"per9":0,"per10":0,"per11":0},{"date":"2025-11-05","name":"马可波罗","code":"001386","remark":"净卖: -1353.89万","price":0,"oprice":0,"cprice":0,"per":0,"per0":0,"per1":0,"per2":0,"per3":0,"per4":0,"per5":0,"per6":0,"per7":0,"per8":0,"per9":0,"per10":0,"per11":0},{"date":"2025-11-07","name":"远达环保","code":"600292","remark":"净买: 3723.16万","price":0,"oprice":0,"cprice":0,"per":0,"per0":0,"per1":0,"per2":0,"per3":0,"per4":0,"per5":0,"per6":0,"per7":0,"per8":0,"per9":0,"per10":0,"per11":0},{"date":"2025-11-10","name":"时空科技","code":"605178","remark":"净买: 3596.94万","price":0,"oprice":0,"cprice":0,"per":0,"per0":0,"per1":0,"per2":0,"per3":0,"per4":0,"per5":0,"per6":0,"per7":0,"per8":0,"per9":0,"per10":0,"per11":0},{"date":"2025-11-11","name":"时空科技","code":"605178","remark":"净买: 2131.60万","price":0,"oprice":0,"cprice":0,"per":0,"per0":0,"per1":0,"per2":0,"per3":0,"per4":0,"per5":0,"per6":0,"per7":0,"per8":0,"per9":0,"per10":0,"per11":0},{"date":"2025-11-12","name":"安泰集团","code":"600408","remark":"净买: 3773.80万","price":0,"oprice":0,"cprice":0,"per":0,"per0":0,"per1":0,"per2":0,"per3":0,"per4":0,"per5":0,"per6":0,"per7":0,"per8":0,"per9":0,"per10":0,"per11":0},{"date":"2025-11-14","name":"安泰集团","code":"600408","remark":"净卖: -5079.61万","price":0,"oprice":0,"cprice":0,"per":0,"per0":0,"per1":0,"per2":0,"per3":0,"per4":0,"per5":0,"per6":0,"per7":0,"per8":0,"per9":0,"per10":0,"per11":0},{"date":"2025-11-14","name":"时空科技","code":"605178","remark":"净买: 6264.81万","price":0,"oprice":0,"cprice":0,"per":0,"per0":0,"per1":0,"per2":0,"per3":0,"per4":0,"per5":0,"per6":0,"per7":0,"per8":0,"per9":0,"per10":0,"per11":0},{"date":"2025-11-17","name":"时空科技","code":"605178","remark":"净卖: -3930.85万","price":0,"oprice":0,"cprice":0,"per":0,"per0":0,"per1":0,"per2":0,"per3":0,"per4":0,"per5":0,"per6":0,"per7":0,"per8":0,"per9":0,"per10":0,"per11":0},{"date":"2025-11-19","name":"合肥城建","code":"002208","remark":"净买: 2932.87万","price":0,"oprice":0,"cprice":0,"per":0,"per0":0,"per1":0,"per2":0,"per3":0,"per4":0,"per5":0,"per6":0,"per7":0,"per8":0,"per9":0,"per10":0,"per11":0},{"date":"2025-11-21","name":"榕基软件","code":"002474","remark":"净买: 6255.96万","price":0,"oprice":0,"cprice":0,"per":0,"per0":0,"per1":0,"per2":0,"per3":0,"per4":0,"per5":0,"per6":0,"per7":0,"per8":0,"per9":0,"per10":0,"per11":0},{"date":"2025-11-24","name":"榕基软件","code":"002474","remark":"净卖: -8288.69万","price":0,"oprice":0,"cprice":0,"per":0,"per0":0,"per1":0,"per2":0,"per3":0,"per4":0,"per5":0,"per6":0,"per7":0,"per8":0,"per9":0,"per10":0,"per11":0},{"date":"2025-11-24","name":"合肥城建","code":"002208","remark":"净卖: -8486.84万","price":0,"oprice":0,"cprice":0,"per":0,"per0":0,"per1":0,"per2":0,"per3":0,"per4":0,"per5":0,"per6":0,"per7":0,"per8":0,"per9":0,"per10":0,"per11":0},{"date":"2025-11-25","name":"榕基软件","code":"002474","remark":"净卖: -381.05万","price":0,"oprice":0,"cprice":0,"per":0,"per0":0,"per1":0,"per2":0,"per3":0,"per4":0,"per5":0,"per6":0,"per7":0,"per8":0,"per9":0,"per10":0,"per11":0},{"date":"2025-11-27","name":"特发信息","code":"000070","remark":"净买: 5870.62万","price":0,"oprice":0,"cprice":0,"per":0,"per0":0,"per1":0,"per2":0,"per3":0,"per4":0,"per5":0,"per6":0,"per7":0,"per8":0,"per9":0,"per10":0,"per11":0},{"date":"2025-11-28","name":"浪潮软件","code":"600756","remark":"净买: 3119.61万","price":0,"oprice":0,"cprice":0,"per":0,"per0":0,"per1":0,"per2":0,"per3":0,"per4":0,"per5":0,"per6":0,"per7":0,"per8":0,"per9":0,"per10":0,"per11":0},{"date":"2025-12-03","name":"中国铀业","code":"001280","remark":"净买: 8385.01万","price":0,"oprice":0,"cprice":0,"per":0,"per0":0,"per1":0,"per2":0,"per3":0,"per4":0,"per5":0,"per6":0,"per7":0,"per8":0,"per9":0,"per10":0,"per11":0},{"date":"2025-12-03","name":"浪潮软件","code":"600756","remark":"净卖: -4201.18万","price":0,"oprice":0,"cprice":0,"per":0,"per0":0,"per1":0,"per2":0,"per3":0,"per4":0,"per5":0,"per6":0,"per7":0,"per8":0,"per9":0,"per10":0,"per11":0},{"date":"2025-12-08","name":"三木集团","code":"000632","remark":"净卖: -3133.98万","price":0,"oprice":0,"cprice":0,"per":0,"per0":0,"per1":0,"per2":0,"per3":0,"per4":0,"per5":0,"per6":0,"per7":0,"per8":0,"per9":0,"per10":0,"per11":0},{"date":"2025-12-11","name":"中国铀业","code":"001280","remark":"净卖: -2.10亿","price":0,"oprice":0,"cprice":0,"per":0,"per0":0,"per1":0,"per2":0,"per3":0,"per4":0,"per5":0,"per6":0,"per7":0,"per8":0,"per9":0,"per10":0,"per11":0},{"date":"2025-12-11","name":"航天动力","code":"600343","remark":"净买: 9198.92万","price":0,"oprice":0,"cprice":0,"per":0,"per0":0,"per1":0,"per2":0,"per3":0,"per4":0,"per5":0,"per6":0,"per7":0,"per8":0,"per9":0,"per10":0,"per11":0},{"date":"2025-12-12","name":"三木集团","code":"000632","remark":"净卖: -421.33万","price":0,"oprice":0,"cprice":0,"per":0,"per0":0,"per1":0,"per2":0,"per3":0,"per4":0,"per5":0,"per6":0,"per7":0,"per8":0,"per9":0,"per10":0,"per11":0},{"date":"2025-12-12","name":"顺灏股份","code":"002565","remark":"净卖: -2209.96万","price":0,"oprice":0,"cprice":0,"per":0,"per0":0,"per1":0,"per2":0,"per3":0,"per4":0,"per5":0,"per6":0,"per7":0,"per8":0,"per9":0,"per10":0,"per11":0},{"date":"2025-12-12","name":"西部材料","code":"002149","remark":"净买: 9078.74万","price":0,"oprice":0,"cprice":0,"per":0,"per0":0,"per1":0,"per2":0,"per3":0,"per4":0,"per5":0,"per6":0,"per7":0,"per8":0,"per9":0,"per10":0,"per11":0},{"date":"2025-12-15","name":"东百集团","code":"600693","remark":"净买: 6515.73万","price":0,"oprice":0,"cprice":0,"per":0,"per0":0,"per1":0,"per2":0,"per3":0,"per4":0,"per5":0,"per6":0,"per7":0,"per8":0,"per9":0,"per10":0,"per11":0},{"date":"2025-12-15","name":"西部材料","code":"002149","remark":"净卖: -9873.31万","price":0,"oprice":0,"cprice":0,"per":0,"per0":0,"per1":0,"per2":0,"per3":0,"per4":0,"per5":0,"per6":0,"per7":0,"per8":0,"per9":0,"per10":0,"per11":0},{"date":"2025-12-16","name":"通宇通讯","code":"002792","remark":"净卖: -2564.02万","price":0,"oprice":0,"cprice":0,"per":0,"per0":0,"per1":0,"per2":0,"per3":0,"per4":0,"per5":0,"per6":0,"per7":0,"per8":0,"per9":0,"per10":0,"per11":0},{"date":"2025-12-16","name":"四川金顶","code":"600678","remark":"净买: 4108.17万","price":0,"oprice":0,"cprice":0,"per":0,"per0":0,"per1":0,"per2":0,"per3":0,"per4":0,"per5":0,"per6":0,"per7":0,"per8":0,"per9":0,"per10":0,"per11":0},{"date":"2025-12-16","name":"三木集团","code":"000632","remark":"净卖: -1456.53万","price":0,"oprice":0,"cprice":0,"per":0,"per0":0,"per1":0,"per2":0,"per3":0,"per4":0,"per5":0,"per6":0,"per7":0,"per8":0,"per9":0,"per10":0,"per11":0},{"date":"2025-12-17","name":"*ST奥维","code":"002231","remark":"净卖: -49.68万","price":0,"oprice":0,"cprice":0,"per":0,"per0":0,"per1":0,"per2":0,"per3":0,"per4":0,"per5":0,"per6":0,"per7":0,"per8":0,"per9":0,"per10":0,"per11":0},{"date":"2025-12-17","name":"四川金顶","code":"600678","remark":"净卖: -3492.50万","price":0,"oprice":0,"cprice":0,"per":0,"per0":0,"per1":0,"per2":0,"per3":0,"per4":0,"per5":0,"per6":0,"per7":0,"per8":0,"per9":0,"per10":0,"per11":0},{"date":"2025-12-17","name":"西部材料","code":"002149","remark":"净买: 9368.27万","price":0,"oprice":0,"cprice":0,"per":0,"per0":0,"per1":0,"per2":0,"per3":0,"per4":0,"per5":0,"per6":0,"per7":0,"per8":0,"per9":0,"per10":0,"per11":0},{"date":"2025-12-18","name":"西部材料","code":"002149","remark":"净卖: -5002.83万","price":0,"oprice":0,"cprice":0,"per":0,"per0":0,"per1":0,"per2":0,"per3":0,"per4":0,"per5":0,"per6":0,"per7":0,"per8":0,"per9":0,"per10":0,"per11":0},{"date":"2025-12-18","name":"万隆光电","code":"300710","remark":"净卖: -319.30万","price":0,"oprice":0,"cprice":0,"per":0,"per0":0,"per1":0,"per2":0,"per3":0,"per4":0,"per5":0,"per6":0,"per7":0,"per8":0,"per9":0,"per10":0,"per11":0},{"date":"2025-12-18","name":"东百集团","code":"600693","remark":"净卖: -5878.59万","price":0,"oprice":0,"cprice":0,"per":0,"per0":0,"per1":0,"per2":0,"per3":0,"per4":0,"per5":0,"per6":0,"per7":0,"per8":0,"per9":0,"per10":0,"per11":0},{"date":"2025-12-19","name":"西部材料","code":"002149","remark":"净卖: -1.04亿","price":0,"oprice":0,"cprice":0,"per":0,"per0":0,"per1":0,"per2":0,"per3":0,"per4":0,"per5":0,"per6":0,"per7":0,"per8":0,"per9":0,"per10":0,"per11":0},{"date":"2025-12-22","name":"*ST立方","code":"300344","remark":"净买: 162.68万","price":0,"oprice":0,"cprice":0,"per":0,"per0":0,"per1":0,"per2":0,"per3":0,"per4":0,"per5":0,"per6":0,"per7":0,"per8":0,"per9":0,"per10":0,"per11":0},{"date":"2025-12-26","name":"优迅股份","code":"688807","remark":"净买: 2936.62万","price":0,"oprice":0,"cprice":0,"per":0,"per0":0,"per1":0,"per2":0,"per3":0,"per4":0,"per5":0,"per6":0,"per7":0,"per8":0,"per9":0,"per10":0,"per11":0},{"date":"2026-01-05","name":"三房巷","code":"600370","remark":"净买: 1059.95万","price":0,"oprice":0,"cprice":0,"per":0,"per0":0,"per1":0,"per2":0,"per3":0,"per4":0,"per5":0,"per6":0,"per7":0,"per8":0,"per9":0,"per10":0,"per11":0},{"date":"2026-01-06","name":"三房巷","code":"600370","remark":"净卖: -1074.49万","price":0,"oprice":0,"cprice":0,"per":0,"per0":0,"per1":0,"per2":0,"per3":0,"per4":0,"per5":0,"per6":0,"per7":0,"per8":0,"per9":0,"per10":0,"per11":0},{"date":"2026-01-12","name":"德龙汇能","code":"000593","remark":"净买: 3480.01万","price":0,"oprice":0,"cprice":0,"per":0,"per0":0,"per1":0,"per2":0,"per3":0,"per4":0,"per5":0,"per6":0,"per7":0,"per8":0,"per9":0,"per10":0,"per11":0},{"date":"2026-01-14","name":"神剑股份","code":"002361","remark":"净卖: -5232.17万","price":0,"oprice":0,"cprice":0,"per":0,"per0":0,"per1":0,"per2":0,"per3":0,"per4":0,"per5":0,"per6":0,"per7":0,"per8":0,"per9":0,"per10":0,"per11":0},{"date":"2026-01-14","name":"德龙汇能","code":"000593","remark":"净卖: -3784.56万","price":0,"oprice":0,"cprice":0,"per":0,"per0":0,"per1":0,"per2":0,"per3":0,"per4":0,"per5":0,"per6":0,"per7":0,"per8":0,"per9":0,"per10":0,"per11":0},{"date":"2026-01-16","name":"华菱线缆","code":"001208","remark":"净买: 2508.61万","price":0,"oprice":0,"cprice":0,"per":0,"per0":0,"per1":0,"per2":0,"per3":0,"per4":0,"per5":0,"per6":0,"per7":0,"per8":0,"per9":0,"per10":0,"per11":0},{"date":"2026-01-19","name":"神剑股份","code":"002361","remark":"净卖: -3348.61万","price":0,"oprice":0,"cprice":0,"per":0,"per0":0,"per1":0,"per2":0,"per3":0,"per4":0,"per5":0,"per6":0,"per7":0,"per8":0,"per9":0,"per10":0,"per11":0},{"date":"2026-01-19","name":"航天动力","code":"600343","remark":"净卖: -359.86万","price":0,"oprice":0,"cprice":0,"per":0,"per0":0,"per1":0,"per2":0,"per3":0,"per4":0,"per5":0,"per6":0,"per7":0,"per8":0,"per9":0,"per10":0,"per11":0},{"date":"2026-01-19","name":"城建发展","code":"600266","remark":"净卖: -4957.03万","price":0,"oprice":0,"cprice":0,"per":0,"per0":0,"per1":0,"per2":0,"per3":0,"per4":0,"per5":0,"per6":0,"per7":0,"per8":0,"per9":0,"per10":0,"per11":0},{"date":"2026-01-23","name":"蓝箭电子","code":"301348","remark":"净买: 2663.62万","price":0,"oprice":0,"cprice":0,"per":0,"per0":0,"per1":0,"per2":0,"per3":0,"per4":0,"per5":0,"per6":0,"per7":0,"per8":0,"per9":0,"per10":0,"per11":0},{"date":"2026-01-27","name":"大位科技","code":"600589","remark":"净买: 8786.02万","price":0,"oprice":0,"cprice":0,"per":0,"per0":0,"per1":0,"per2":0,"per3":0,"per4":0,"per5":0,"per6":0,"per7":0,"per8":0,"per9":0,"per10":0,"per11":0},{"date":"2026-01-28","name":"*ST岩石","code":"600696","remark":"净卖: -106.59万","price":0,"oprice":0,"cprice":0,"per":0,"per0":0,"per1":0,"per2":0,"per3":0,"per4":0,"per5":0,"per6":0,"per7":0,"per8":0,"per9":0,"per10":0,"per11":0},{"date":"2026-01-29","name":"世纪恒通","code":"301428","remark":"净买: 1936.34万","price":0,"oprice":0,"cprice":0,"per":0,"per0":0,"per1":0,"per2":0,"per3":0,"per4":0,"per5":0,"per6":0,"per7":0,"per8":0,"per9":0,"per10":0,"per11":0},{"date":"2026-01-30","name":"世纪恒通","code":"301428","remark":"净卖: -1818.07万","price":0,"oprice":0,"cprice":0,"per":0,"per0":0,"per1":0,"per2":0,"per3":0,"per4":0,"per5":0,"per6":0,"per7":0,"per8":0,"per9":0,"per10":0,"per11":0},{"date":"2026-02-04","name":"海兰信","code":"300065","remark":"净买: 5490.67万","price":0,"oprice":0,"cprice":0,"per":0,"per0":0,"per1":0,"per2":0,"per3":0,"per4":0,"per5":0,"per6":0,"per7":0,"per8":0,"per9":0,"per10":0,"per11":0},{"date":"2026-02-04","name":"浙文互联","code":"600986","remark":"净买: 1.09亿","price":0,"oprice":0,"cprice":0,"per":0,"per0":0,"per1":0,"per2":0,"per3":0,"per4":0,"per5":0,"per6":0,"per7":0,"per8":0,"per9":0,"per10":0,"per11":0},{"date":"2026-02-06","name":"浙文互联","code":"600986","remark":"净卖: -1.00亿","price":0,"oprice":0,"cprice":0,"per":0,"per0":0,"per1":0,"per2":0,"per3":0,"per4":0,"per5":0,"per6":0,"per7":0,"per8":0,"per9":0,"per10":0,"per11":0},{"date":"2026-02-10","name":"大位科技","code":"600589","remark":"净买: 8721.30万","price":0,"oprice":0,"cprice":0,"per":0,"per0":0,"per1":0,"per2":0,"per3":0,"per4":0,"per5":0,"per6":0,"per7":0,"per8":0,"per9":0,"per10":0,"per11":0},{"date":"2026-02-12","name":"首都在线","code":"300846","remark":"净买: 6790.52万","price":0,"oprice":0,"cprice":0,"per":0,"per0":0,"per1":0,"per2":0,"per3":0,"per4":0,"per5":0,"per6":0,"per7":0,"per8":0,"per9":0,"per10":0,"per11":0},{"date":"2026-02-13","name":"海量数据","code":"603138","remark":"净买: 2487.26万","price":0,"oprice":0,"cprice":0,"per":0,"per0":0,"per1":0,"per2":0,"per3":0,"per4":0,"per5":0,"per6":0,"per7":0,"per8":0,"per9":0,"per10":0,"per11":0},{"date":"2026-02-13","name":"杭电股份","code":"603618","remark":"净买: 5036.69万","price":0,"oprice":0,"cprice":0,"per":0,"per0":0,"per1":0,"per2":0,"per3":0,"per4":0,"per5":0,"per6":0,"per7":0,"per8":0,"per9":0,"per10":0,"per11":0},{"date":"2026-02-24","name":"首都在线","code":"300846","remark":"净卖: -1.02亿","price":0,"oprice":0,"cprice":0,"per":0,"per0":0,"per1":0,"per2":0,"per3":0,"per4":0,"per5":0,"per6":0,"per7":0,"per8":0,"per9":0,"per10":0,"per11":0},{"date":"2026-02-24","name":"大位科技","code":"600589","remark":"净卖: -1.63亿","price":0,"oprice":0,"cprice":0,"per":0,"per0":0,"per1":0,"per2":0,"per3":0,"per4":0,"per5":0,"per6":0,"per7":0,"per8":0,"per9":0,"per10":0,"per11":0},{"date":"2026-02-25","name":"豫能控股","code":"001896","remark":"净买: 6794.32万","price":0,"oprice":0,"cprice":0,"per":0,"per0":0,"per1":0,"per2":0,"per3":0,"per4":0,"per5":0,"per6":0,"per7":0,"per8":0,"per9":0,"per10":0,"per11":0},{"date":"2026-02-26","name":"润泽科技","code":"300442","remark":"净买: 594.95万","price":0,"oprice":0,"cprice":0,"per":0,"per0":0,"per1":0,"per2":0,"per3":0,"per4":0,"per5":0,"per6":0,"per7":0,"per8":0,"per9":0,"per10":0,"per11":0},{"date":"2026-02-27","name":"豫能控股","code":"001896","remark":"净卖: -6704.87万","price":0,"oprice":0,"cprice":0,"per":0,"per0":0,"per1":0,"per2":0,"per3":0,"per4":0,"per5":0,"per6":0,"per7":0,"per8":0,"per9":0,"per10":0,"per11":0},{"date":"2026-02-27","name":"云天励飞","code":"688343","remark":"净买: 1.94亿","price":0,"oprice":0,"cprice":0,"per":0,"per0":0,"per1":0,"per2":0,"per3":0,"per4":0,"per5":0,"per6":0,"per7":0,"per8":0,"per9":0,"per10":0,"per11":0},{"date":"2026-03-03","name":"泰嘉股份","code":"002843","remark":"净买: 7749.96万","price":0,"oprice":0,"cprice":0,"per":0,"per0":0,"per1":0,"per2":0,"per3":0,"per4":0,"per5":0,"per6":0,"per7":0,"per8":0,"per9":0,"per10":0,"per11":0},{"date":"2026-03-05","name":"川润股份","code":"002272","remark":"净买: 5705.47万","price":0,"oprice":0,"cprice":0,"per":0,"per0":0,"per1":0,"per2":0,"per3":0,"per4":0,"per5":0,"per6":0,"per7":0,"per8":0,"per9":0,"per10":0,"per11":0},{"date":"2026-03-06","name":"泰嘉股份","code":"002843","remark":"净卖: -1.35亿","price":0,"oprice":0,"cprice":0,"per":0,"per0":0,"per1":0,"per2":0,"per3":0,"per4":0,"per5":0,"per6":0,"per7":0,"per8":0,"per9":0,"per10":0,"per11":0},{"date":"2026-03-10","name":"科华数据","code":"002335","remark":"净买: 9678.79万","price":0,"oprice":0,"cprice":0,"per":0,"per0":0,"per1":0,"per2":0,"per3":0,"per4":0,"per5":0,"per6":0,"per7":0,"per8":0,"per9":0,"per10":0,"per11":0},{"date":"2026-03-13","name":"固德电材","code":"301680","remark":"净买: 701.69万","price":0,"oprice":0,"cprice":0,"per":0,"per0":0,"per1":0,"per2":0,"per3":0,"per4":0,"per5":0,"per6":0,"per7":0,"per8":0,"per9":0,"per10":0,"per11":0},{"date":"2026-03-13","name":"豫能控股","code":"001896","remark":"净买: 2440.07万","price":0,"oprice":0,"cprice":0,"per":0,"per0":0,"per1":0,"per2":0,"per3":0,"per4":0,"per5":0,"per6":0,"per7":0,"per8":0,"per9":0,"per10":0,"per11":0},{"date":"2026-03-13","name":"首航新能","code":"301658","remark":"净买: 1421.23万","price":0,"oprice":0,"cprice":0,"per":0,"per0":0,"per1":0,"per2":0,"per3":0,"per4":0,"per5":0,"per6":0,"per7":0,"per8":0,"per9":0,"per10":0,"per11":0},{"date":"2026-03-16","name":"固德电材","code":"301680","remark":"净卖: -1103.73万","price":0,"oprice":0,"cprice":0,"per":0,"per0":0,"per1":0,"per2":0,"per3":0,"per4":0,"per5":0,"per6":0,"per7":0,"per8":0,"per9":0,"per10":0,"per11":0},{"date":"2026-03-16","name":"首航新能","code":"301658","remark":"净卖: -1195.77万","price":0,"oprice":0,"cprice":0,"per":0,"per0":0,"per1":0,"per2":0,"per3":0,"per4":0,"per5":0,"per6":0,"per7":0,"per8":0,"per9":0,"per10":0,"per11":0},{"date":"2026-03-18","name":"爱得科技","code":"920180","remark":"净卖: -202.41万","price":0,"oprice":0,"cprice":0,"per":0,"per0":0,"per1":0,"per2":0,"per3":0,"per4":0,"per5":0,"per6":0,"per7":0,"per8":0,"per9":0,"per10":0,"per11":0},{"date":"2026-03-18","name":"中南文化","code":"002445","remark":"净卖: -5406.85万","price":0,"oprice":0,"cprice":0,"per":0,"per0":0,"per1":0,"per2":0,"per3":0,"per4":0,"per5":0,"per6":0,"per7":0,"per8":0,"per9":0,"per10":0,"per11":0},{"date":"2026-03-19","name":"东方新能","code":"002310","remark":"净卖: -2161.93万","price":0,"oprice":0,"cprice":0,"per":0,"per0":0,"per1":0,"per2":0,"per3":0,"per4":0,"per5":0,"per6":0,"per7":0,"per8":0,"per9":0,"per10":0,"per11":0},{"date":"2026-03-20","name":"利通电子","code":"603629","remark":"净买: 5587.95万","price":0,"oprice":0,"cprice":0,"per":0,"per0":0,"per1":0,"per2":0,"per3":0,"per4":0,"per5":0,"per6":0,"per7":0,"per8":0,"per9":0,"per10":0,"per11":0},{"date":"2026-03-30","name":"百川股份","code":"002455","remark":"净买: 9631.73万","price":0,"oprice":0,"cprice":0,"per":0,"per0":0,"per1":0,"per2":0,"per3":0,"per4":0,"per5":0,"per6":0,"per7":0,"per8":0,"per9":0,"per10":0,"per11":0},{"date":"2026-03-31","name":"交大铁发","code":"920027","remark":"净卖: -604.37万","price":0,"oprice":0,"cprice":0,"per":0,"per0":0,"per1":0,"per2":0,"per3":0,"per4":0,"per5":0,"per6":0,"per7":0,"per8":0,"per9":0,"per10":0,"per11":0},{"date":"2026-04-07","name":"立方退","code":"300344","remark":"净买: 103.00万","price":0,"oprice":0,"cprice":0,"per":0,"per0":0,"per1":0,"per2":0,"per3":0,"per4":0,"per5":0,"per6":0,"per7":0,"per8":0,"per9":0,"per10":0,"per11":0},{"date":"2026-04-13","name":"立方退","code":"300344","remark":"净买: 73.74万","price":0,"oprice":0,"cprice":0,"per":0,"per0":0,"per1":0,"per2":0,"per3":0,"per4":0,"per5":0,"per6":0,"per7":0,"per8":0,"per9":0,"per10":0,"per11":0},{"date":"2026-04-14","name":"立方退","code":"300344","remark":"净卖: -86.71万","price":0,"oprice":0,"cprice":0,"per":0,"per0":0,"per1":0,"per2":0,"per3":0,"per4":0,"per5":0,"per6":0,"per7":0,"per8":0,"per9":0,"per10":0,"per11":0},{"date":"2026-04-15","name":"长城科技","code":"603897","remark":"净买: 4070.93万","price":0,"oprice":0,"cprice":0,"per":0,"per0":0,"per1":0,"per2":0,"per3":0,"per4":0,"per5":0,"per6":0,"per7":0,"per8":0,"per9":0,"per10":0,"per11":0},{"date":"2026-04-15","name":"族兴新材","code":"920078","remark":"净买: 221.98万","price":0,"oprice":0,"cprice":0,"per":0,"per0":0,"per1":0,"per2":0,"per3":0,"per4":0,"per5":0,"per6":0,"per7":0,"per8":0,"per9":0,"per10":0,"per11":0},{"date":"2026-04-16","name":"长信科技","code":"300088","remark":"净买: 1.23亿","price":0,"oprice":0,"cprice":0,"per":0,"per0":0,"per1":0,"per2":0,"per3":0,"per4":0,"per5":0,"per6":0,"per7":0,"per8":0,"per9":0,"per10":0,"per11":0},{"date":"2026-04-20","name":"豫能控股","code":"001896","remark":"净买: 7143.98万","price":0,"oprice":0,"cprice":0,"per":0,"per0":0,"per1":0,"per2":0,"per3":0,"per4":0,"per5":0,"per6":0,"per7":0,"per8":0,"per9":0,"per10":0,"per11":0}]