[{"date":"2025-02-05","name":"卓创资讯","code":"301299","remark":"净卖: -3475.60万","price":0,"oprice":0,"cprice":0,"per":0,"per0":0,"per1":0,"per2":0,"per3":0,"per4":0,"per5":0,"per6":0,"per7":0,"per8":0,"per9":0,"per10":0,"per11":0},{"date":"2025-02-06","name":"领益智造","code":"002600","remark":"净买: 9636.70万","price":0,"oprice":0,"cprice":0,"per":0,"per0":0,"per1":0,"per2":0,"per3":0,"per4":0,"per5":0,"per6":0,"per7":0,"per8":0,"per9":0,"per10":0,"per11":0},{"date":"2025-02-11","name":"优刻得","code":"688158","remark":"净买: 3859.85万","price":0,"oprice":0,"cprice":0,"per":0,"per0":0,"per1":0,"per2":0,"per3":0,"per4":0,"per5":0,"per6":0,"per7":0,"per8":0,"per9":0,"per10":0,"per11":0},{"date":"2025-02-11","name":"居然智家","code":"000785","remark":"净卖: -1085.38万","price":0,"oprice":0,"cprice":0,"per":0,"per0":0,"per1":0,"per2":0,"per3":0,"per4":0,"per5":0,"per6":0,"per7":0,"per8":0,"per9":0,"per10":0,"per11":0},{"date":"2025-02-13","name":"创业黑马","code":"300688","remark":"净卖: -2905.03万","price":0,"oprice":0,"cprice":0,"per":0,"per0":0,"per1":0,"per2":0,"per3":0,"per4":0,"per5":0,"per6":0,"per7":0,"per8":0,"per9":0,"per10":0,"per11":0},{"date":"2025-02-13","name":"卧龙电驱","code":"600580","remark":"净卖: -1.03亿","price":0,"oprice":0,"cprice":0,"per":0,"per0":0,"per1":0,"per2":0,"per3":0,"per4":0,"per5":0,"per6":0,"per7":0,"per8":0,"per9":0,"per10":0,"per11":0},{"date":"2025-02-14","name":"杭钢股份","code":"600126","remark":"净买: 2.59亿","price":0,"oprice":0,"cprice":0,"per":0,"per0":0,"per1":0,"per2":0,"per3":0,"per4":0,"per5":0,"per6":0,"per7":0,"per8":0,"per9":0,"per10":0,"per11":0},{"date":"2025-02-14","name":"优刻得","code":"688158","remark":"净买: 6971.52万","price":0,"oprice":0,"cprice":0,"per":0,"per0":0,"per1":0,"per2":0,"per3":0,"per4":0,"per5":0,"per6":0,"per7":0,"per8":0,"per9":0,"per10":0,"per11":0},{"date":"2025-02-18","name":"梦网科技","code":"002123","remark":"净卖: -4164.93万","price":0,"oprice":0,"cprice":0,"per":0,"per0":0,"per1":0,"per2":0,"per3":0,"per4":0,"per5":0,"per6":0,"per7":0,"per8":0,"per9":0,"per10":0,"per11":0},{"date":"2025-02-19","name":"北自科技","code":"603082","remark":"净卖: -1225.33万","price":0,"oprice":0,"cprice":0,"per":0,"per0":0,"per1":0,"per2":0,"per3":0,"per4":0,"per5":0,"per6":0,"per7":0,"per8":0,"per9":0,"per10":0,"per11":0},{"date":"2025-02-20","name":"奥飞数据","code":"300738","remark":"净买: 7457.10万","price":0,"oprice":0,"cprice":0,"per":0,"per0":0,"per1":0,"per2":0,"per3":0,"per4":0,"per5":0,"per6":0,"per7":0,"per8":0,"per9":0,"per10":0,"per11":0},{"date":"2025-02-21","name":"奥飞数据","code":"300738","remark":"净买: 3733.98万","price":0,"oprice":0,"cprice":0,"per":0,"per0":0,"per1":0,"per2":0,"per3":0,"per4":0,"per5":0,"per6":0,"per7":0,"per8":0,"per9":0,"per10":0,"per11":0},{"date":"2025-02-24","name":"盈峰环境","code":"000967","remark":"净卖: -5789.31万","price":0,"oprice":0,"cprice":0,"per":0,"per0":0,"per1":0,"per2":0,"per3":0,"per4":0,"per5":0,"per6":0,"per7":0,"per8":0,"per9":0,"per10":0,"per11":0},{"date":"2025-02-24","name":"科华数据","code":"002335","remark":"净买: 6951.88万","price":0,"oprice":0,"cprice":0,"per":0,"per0":0,"per1":0,"per2":0,"per3":0,"per4":0,"per5":0,"per6":0,"per7":0,"per8":0,"per9":0,"per10":0,"per11":0},{"date":"2025-02-25","name":"杭钢股份","code":"600126","remark":"净卖: -9947.40万","price":0,"oprice":0,"cprice":0,"per":0,"per0":0,"per1":0,"per2":0,"per3":0,"per4":0,"per5":0,"per6":0,"per7":0,"per8":0,"per9":0,"per10":0,"per11":0},{"date":"2025-03-03","name":"宏景科技","code":"301396","remark":"净买: 2230.27万","price":0,"oprice":0,"cprice":0,"per":0,"per0":0,"per1":0,"per2":0,"per3":0,"per4":0,"per5":0,"per6":0,"per7":0,"per8":0,"per9":0,"per10":0,"per11":0},{"date":"2025-03-03","name":"德明利","code":"001309","remark":"净卖: -4848.24万","price":0,"oprice":0,"cprice":0,"per":0,"per0":0,"per1":0,"per2":0,"per3":0,"per4":0,"per5":0,"per6":0,"per7":0,"per8":0,"per9":0,"per10":0,"per11":0},{"date":"2025-03-05","name":"宏景科技","code":"301396","remark":"净买: 3981.84万","price":0,"oprice":0,"cprice":0,"per":0,"per0":0,"per1":0,"per2":0,"per3":0,"per4":0,"per5":0,"per6":0,"per7":0,"per8":0,"per9":0,"per10":0,"per11":0},{"date":"2025-03-06","name":"宏景科技","code":"301396","remark":"净卖: -4487.67万","price":0,"oprice":0,"cprice":0,"per":0,"per0":0,"per1":0,"per2":0,"per3":0,"per4":0,"per5":0,"per6":0,"per7":0,"per8":0,"per9":0,"per10":0,"per11":0},{"date":"2025-03-10","name":"英诺激光","code":"301021","remark":"净买: 4044.32万","price":0,"oprice":0,"cprice":0,"per":0,"per0":0,"per1":0,"per2":0,"per3":0,"per4":0,"per5":0,"per6":0,"per7":0,"per8":0,"per9":0,"per10":0,"per11":0},{"date":"2025-03-11","name":"*ST宁科","code":"600165","remark":"净卖: -308.14万","price":0,"oprice":0,"cprice":0,"per":0,"per0":0,"per1":0,"per2":0,"per3":0,"per4":0,"per5":0,"per6":0,"per7":0,"per8":0,"per9":0,"per10":0,"per11":0},{"date":"2025-03-13","name":"南兴股份","code":"002757","remark":"净卖: -2190.73万","price":0,"oprice":0,"cprice":0,"per":0,"per0":0,"per1":0,"per2":0,"per3":0,"per4":0,"per5":0,"per6":0,"per7":0,"per8":0,"per9":0,"per10":0,"per11":0},{"date":"2025-03-13","name":"宏景科技","code":"301396","remark":"净卖: -3307.69万","price":0,"oprice":0,"cprice":0,"per":0,"per0":0,"per1":0,"per2":0,"per3":0,"per4":0,"per5":0,"per6":0,"per7":0,"per8":0,"per9":0,"per10":0,"per11":0},{"date":"2025-03-13","name":"利通电子","code":"603629","remark":"净卖: -3257.00万","price":0,"oprice":0,"cprice":0,"per":0,"per0":0,"per1":0,"per2":0,"per3":0,"per4":0,"per5":0,"per6":0,"per7":0,"per8":0,"per9":0,"per10":0,"per11":0},{"date":"2025-03-13","name":"国脉科技","code":"002093","remark":"净买: 3977.67万","price":0,"oprice":0,"cprice":0,"per":0,"per0":0,"per1":0,"per2":0,"per3":0,"per4":0,"per5":0,"per6":0,"per7":0,"per8":0,"per9":0,"per10":0,"per11":0},{"date":"2025-03-14","name":"杭钢股份","code":"600126","remark":"净买: 4706.84万","price":0,"oprice":0,"cprice":0,"per":0,"per0":0,"per1":0,"per2":0,"per3":0,"per4":0,"per5":0,"per6":0,"per7":0,"per8":0,"per9":0,"per10":0,"per11":0},{"date":"2025-03-18","name":"大位科技","code":"600589","remark":"净买: 5449.32万","price":0,"oprice":0,"cprice":0,"per":0,"per0":0,"per1":0,"per2":0,"per3":0,"per4":0,"per5":0,"per6":0,"per7":0,"per8":0,"per9":0,"per10":0,"per11":0},{"date":"2025-03-19","name":"大位科技","code":"600589","remark":"净卖: -5908.82万","price":0,"oprice":0,"cprice":0,"per":0,"per0":0,"per1":0,"per2":0,"per3":0,"per4":0,"per5":0,"per6":0,"per7":0,"per8":0,"per9":0,"per10":0,"per11":0},{"date":"2025-03-20","name":"ST华闻","code":"000793","remark":"净买: 49.86万","price":0,"oprice":0,"cprice":0,"per":0,"per0":0,"per1":0,"per2":0,"per3":0,"per4":0,"per5":0,"per6":0,"per7":0,"per8":0,"per9":0,"per10":0,"per11":0},{"date":"2025-03-25","name":"金城医药","code":"300233","remark":"净买: 5868.12万","price":0,"oprice":0,"cprice":0,"per":0,"per0":0,"per1":0,"per2":0,"per3":0,"per4":0,"per5":0,"per6":0,"per7":0,"per8":0,"per9":0,"per10":0,"per11":0},{"date":"2025-03-25","name":"杭钢股份","code":"600126","remark":"净卖: -3547.96万","price":0,"oprice":0,"cprice":0,"per":0,"per0":0,"per1":0,"per2":0,"per3":0,"per4":0,"per5":0,"per6":0,"per7":0,"per8":0,"per9":0,"per10":0,"per11":0},{"date":"2025-04-07","name":"新赛股份","code":"600540","remark":"净买: 736.33万","price":0,"oprice":0,"cprice":0,"per":0,"per0":0,"per1":0,"per2":0,"per3":0,"per4":0,"per5":0,"per6":0,"per7":0,"per8":0,"per9":0,"per10":0,"per11":0},{"date":"2025-04-07","name":"湘财股份","code":"600095","remark":"净买: 6227.03万","price":0,"oprice":0,"cprice":0,"per":0,"per0":0,"per1":0,"per2":0,"per3":0,"per4":0,"per5":0,"per6":0,"per7":0,"per8":0,"per9":0,"per10":0,"per11":0},{"date":"2025-04-08","name":"青岛金王","code":"002094","remark":"净卖: -15.63万","price":0,"oprice":0,"cprice":0,"per":0,"per0":0,"per1":0,"per2":0,"per3":0,"per4":0,"per5":0,"per6":0,"per7":0,"per8":0,"per9":0,"per10":0,"per11":0},{"date":"2025-04-09","name":"天和磁材","code":"603072","remark":"净卖: -3053.37万","price":0,"oprice":0,"cprice":0,"per":0,"per0":0,"per1":0,"per2":0,"per3":0,"per4":0,"per5":0,"per6":0,"per7":0,"per8":0,"per9":0,"per10":0,"per11":0},{"date":"2025-04-29","name":"宏景科技","code":"301396","remark":"净卖: -4686.80万","price":0,"oprice":0,"cprice":0,"per":0,"per0":0,"per1":0,"per2":0,"per3":0,"per4":0,"per5":0,"per6":0,"per7":0,"per8":0,"per9":0,"per10":0,"per11":0},{"date":"2025-05-12","name":"万向钱潮","code":"000559","remark":"净买: 4520.75万","price":0,"oprice":0,"cprice":0,"per":0,"per0":0,"per1":0,"per2":0,"per3":0,"per4":0,"per5":0,"per6":0,"per7":0,"per8":0,"per9":0,"per10":0,"per11":0},{"date":"2025-05-20","name":"利扬芯片","code":"688135","remark":"净买: 7524.77万","price":0,"oprice":0,"cprice":0,"per":0,"per0":0,"per1":0,"per2":0,"per3":0,"per4":0,"per5":0,"per6":0,"per7":0,"per8":0,"per9":0,"per10":0,"per11":0},{"date":"2025-05-23","name":"先达股份","code":"603086","remark":"净买: 2037.17万","price":0,"oprice":0,"cprice":0,"per":0,"per0":0,"per1":0,"per2":0,"per3":0,"per4":0,"per5":0,"per6":0,"per7":0,"per8":0,"per9":0,"per10":0,"per11":0},{"date":"2025-06-03","name":"诺思兰德","code":"430047","remark":"净卖: -1484.53万","price":0,"oprice":0,"cprice":0,"per":0,"per0":0,"per1":0,"per2":0,"per3":0,"per4":0,"per5":0,"per6":0,"per7":0,"per8":0,"per9":0,"per10":0,"per11":0},{"date":"2025-06-04","name":"御银股份","code":"002177","remark":"净买: 5111.67万","price":0,"oprice":0,"cprice":0,"per":0,"per0":0,"per1":0,"per2":0,"per3":0,"per4":0,"per5":0,"per6":0,"per7":0,"per8":0,"per9":0,"per10":0,"per11":0},{"date":"2025-06-04","name":"中科金财","code":"002657","remark":"净买: 4955.96万","price":0,"oprice":0,"cprice":0,"per":0,"per0":0,"per1":0,"per2":0,"per3":0,"per4":0,"per5":0,"per6":0,"per7":0,"per8":0,"per9":0,"per10":0,"per11":0},{"date":"2025-06-05","name":"御银股份","code":"002177","remark":"净卖: -5285.85万","price":0,"oprice":0,"cprice":0,"per":0,"per0":0,"per1":0,"per2":0,"per3":0,"per4":0,"per5":0,"per6":0,"per7":0,"per8":0,"per9":0,"per10":0,"per11":0},{"date":"2025-06-05","name":"中科金财","code":"002657","remark":"净买: 2141.84万","price":0,"oprice":0,"cprice":0,"per":0,"per0":0,"per1":0,"per2":0,"per3":0,"per4":0,"per5":0,"per6":0,"per7":0,"per8":0,"per9":0,"per10":0,"per11":0},{"date":"2025-06-06","name":"先达股份","code":"603086","remark":"净卖: -5764.32万","price":0,"oprice":0,"cprice":0,"per":0,"per0":0,"per1":0,"per2":0,"per3":0,"per4":0,"per5":0,"per6":0,"per7":0,"per8":0,"per9":0,"per10":0,"per11":0},{"date":"2025-06-10","name":"中科磁业","code":"301141","remark":"净买: 4544.65万","price":0,"oprice":0,"cprice":0,"per":0,"per0":0,"per1":0,"per2":0,"per3":0,"per4":0,"per5":0,"per6":0,"per7":0,"per8":0,"per9":0,"per10":0,"per11":0},{"date":"2025-06-11","name":"雄帝科技","code":"300546","remark":"净买: 3748.58万","price":0,"oprice":0,"cprice":0,"per":0,"per0":0,"per1":0,"per2":0,"per3":0,"per4":0,"per5":0,"per6":0,"per7":0,"per8":0,"per9":0,"per10":0,"per11":0},{"date":"2025-06-12","name":"中科磁业","code":"301141","remark":"净卖: -4075.34万","price":0,"oprice":0,"cprice":0,"per":0,"per0":0,"per1":0,"per2":0,"per3":0,"per4":0,"per5":0,"per6":0,"per7":0,"per8":0,"per9":0,"per10":0,"per11":0},{"date":"2025-06-12","name":"雄帝科技","code":"300546","remark":"净卖: -3556.26万","price":0,"oprice":0,"cprice":0,"per":0,"per0":0,"per1":0,"per2":0,"per3":0,"per4":0,"per5":0,"per6":0,"per7":0,"per8":0,"per9":0,"per10":0,"per11":0},{"date":"2025-06-13","name":"中科磁业","code":"301141","remark":"净卖: -3653.70万","price":0,"oprice":0,"cprice":0,"per":0,"per0":0,"per1":0,"per2":0,"per3":0,"per4":0,"per5":0,"per6":0,"per7":0,"per8":0,"per9":0,"per10":0,"per11":0},{"date":"2025-06-16","name":"天阳科技","code":"300872","remark":"净买: 6162.81万","price":0,"oprice":0,"cprice":0,"per":0,"per0":0,"per1":0,"per2":0,"per3":0,"per4":0,"per5":0,"per6":0,"per7":0,"per8":0,"per9":0,"per10":0,"per11":0},{"date":"2025-06-16","name":"宁波韵升","code":"600366","remark":"净买: 4375.85万","price":0,"oprice":0,"cprice":0,"per":0,"per0":0,"per1":0,"per2":0,"per3":0,"per4":0,"per5":0,"per6":0,"per7":0,"per8":0,"per9":0,"per10":0,"per11":0},{"date":"2025-06-16","name":"恒生电子","code":"600570","remark":"净买: 6445.19万","price":0,"oprice":0,"cprice":0,"per":0,"per0":0,"per1":0,"per2":0,"per3":0,"per4":0,"per5":0,"per6":0,"per7":0,"per8":0,"per9":0,"per10":0,"per11":0},{"date":"2025-06-18","name":"宁波韵升","code":"600366","remark":"净卖: -8881.12万","price":0,"oprice":0,"cprice":0,"per":0,"per0":0,"per1":0,"per2":0,"per3":0,"per4":0,"per5":0,"per6":0,"per7":0,"per8":0,"per9":0,"per10":0,"per11":0},{"date":"2025-06-24","name":"万马科技","code":"300698","remark":"净买: 3148.72万","price":0,"oprice":0,"cprice":0,"per":0,"per0":0,"per1":0,"per2":0,"per3":0,"per4":0,"per5":0,"per6":0,"per7":0,"per8":0,"per9":0,"per10":0,"per11":0},{"date":"2025-07-07","name":"天箭科技","code":"002977","remark":"净卖: -2917.85万","price":0,"oprice":0,"cprice":0,"per":0,"per0":0,"per1":0,"per2":0,"per3":0,"per4":0,"per5":0,"per6":0,"per7":0,"per8":0,"per9":0,"per10":0,"per11":0},{"date":"2025-07-11","name":"北方稀土","code":"600111","remark":"净买: 2.47亿","price":0,"oprice":0,"cprice":0,"per":0,"per0":0,"per1":0,"per2":0,"per3":0,"per4":0,"per5":0,"per6":0,"per7":0,"per8":0,"per9":0,"per10":0,"per11":0},{"date":"2025-07-15","name":"元道通信","code":"301139","remark":"净卖: -1365.99万","price":0,"oprice":0,"cprice":0,"per":0,"per0":0,"per1":0,"per2":0,"per3":0,"per4":0,"per5":0,"per6":0,"per7":0,"per8":0,"per9":0,"per10":0,"per11":0},{"date":"2025-07-18","name":"华宏科技","code":"002645","remark":"净买: 3168.96万","price":0,"oprice":0,"cprice":0,"per":0,"per0":0,"per1":0,"per2":0,"per3":0,"per4":0,"per5":0,"per6":0,"per7":0,"per8":0,"per9":0,"per10":0,"per11":0},{"date":"2025-07-21","name":"华宏科技","code":"002645","remark":"净卖: -3434.37万","price":0,"oprice":0,"cprice":0,"per":0,"per0":0,"per1":0,"per2":0,"per3":0,"per4":0,"per5":0,"per6":0,"per7":0,"per8":0,"per9":0,"per10":0,"per11":0},{"date":"2025-07-22","name":"中国能建","code":"601868","remark":"净买: 5650.60万","price":0,"oprice":0,"cprice":0,"per":0,"per0":0,"per1":0,"per2":0,"per3":0,"per4":0,"per5":0,"per6":0,"per7":0,"per8":0,"per9":0,"per10":0,"per11":0},{"date":"2025-07-24","name":"天齐锂业","code":"002466","remark":"净买: 7610.20万","price":0,"oprice":0,"cprice":0,"per":0,"per0":0,"per1":0,"per2":0,"per3":0,"per4":0,"per5":0,"per6":0,"per7":0,"per8":0,"per9":0,"per10":0,"per11":0},{"date":"2025-07-29","name":"中银证券","code":"601696","remark":"净卖: -5948.87万","price":0,"oprice":0,"cprice":0,"per":0,"per0":0,"per1":0,"per2":0,"per3":0,"per4":0,"per5":0,"per6":0,"per7":0,"per8":0,"per9":0,"per10":0,"per11":0},{"date":"2025-08-04","name":"建设工业","code":"002265","remark":"净买: 4015.26万","price":0,"oprice":0,"cprice":0,"per":0,"per0":0,"per1":0,"per2":0,"per3":0,"per4":0,"per5":0,"per6":0,"per7":0,"per8":0,"per9":0,"per10":0,"per11":0},{"date":"2025-08-08","name":"际华集团","code":"601718","remark":"净买: 7929.22万","price":0,"oprice":0,"cprice":0,"per":0,"per0":0,"per1":0,"per2":0,"per3":0,"per4":0,"per5":0,"per6":0,"per7":0,"per8":0,"per9":0,"per10":0,"per11":0},{"date":"2025-08-11","name":"西部建设","code":"002302","remark":"净卖: -305.33万","price":0,"oprice":0,"cprice":0,"per":0,"per0":0,"per1":0,"per2":0,"per3":0,"per4":0,"per5":0,"per6":0,"per7":0,"per8":0,"per9":0,"per10":0,"per11":0},{"date":"2025-08-11","name":"天齐锂业","code":"002466","remark":"净买: 1.76亿","price":0,"oprice":0,"cprice":0,"per":0,"per0":0,"per1":0,"per2":0,"per3":0,"per4":0,"per5":0,"per6":0,"per7":0,"per8":0,"per9":0,"per10":0,"per11":0},{"date":"2025-08-13","name":"际华集团","code":"601718","remark":"净卖: -4476.29万","price":0,"oprice":0,"cprice":0,"per":0,"per0":0,"per1":0,"per2":0,"per3":0,"per4":0,"per5":0,"per6":0,"per7":0,"per8":0,"per9":0,"per10":0,"per11":0},{"date":"2025-08-14","name":"合百集团","code":"000417","remark":"净卖: -1704.71万","price":0,"oprice":0,"cprice":0,"per":0,"per0":0,"per1":0,"per2":0,"per3":0,"per4":0,"per5":0,"per6":0,"per7":0,"per8":0,"per9":0,"per10":0,"per11":0},{"date":"2025-08-15","name":"伟隆股份","code":"002871","remark":"净买: 2612.85万","price":0,"oprice":0,"cprice":0,"per":0,"per0":0,"per1":0,"per2":0,"per3":0,"per4":0,"per5":0,"per6":0,"per7":0,"per8":0,"per9":0,"per10":0,"per11":0},{"date":"2025-08-18","name":"中科金财","code":"002657","remark":"净卖: -202.22万","price":0,"oprice":0,"cprice":0,"per":0,"per0":0,"per1":0,"per2":0,"per3":0,"per4":0,"per5":0,"per6":0,"per7":0,"per8":0,"per9":0,"per10":0,"per11":0},{"date":"2025-08-18","name":"东信和平","code":"002017","remark":"净买: 4550.13万","price":0,"oprice":0,"cprice":0,"per":0,"per0":0,"per1":0,"per2":0,"per3":0,"per4":0,"per5":0,"per6":0,"per7":0,"per8":0,"per9":0,"per10":0,"per11":0},{"date":"2025-08-22","name":"万通发展","code":"600246","remark":"净买: 1152.99万","price":0,"oprice":0,"cprice":0,"per":0,"per0":0,"per1":0,"per2":0,"per3":0,"per4":0,"per5":0,"per6":0,"per7":0,"per8":0,"per9":0,"per10":0,"per11":0},{"date":"2025-08-26","name":"宏景科技","code":"301396","remark":"净买: 6239.28万","price":0,"oprice":0,"cprice":0,"per":0,"per0":0,"per1":0,"per2":0,"per3":0,"per4":0,"per5":0,"per6":0,"per7":0,"per8":0,"per9":0,"per10":0,"per11":0},{"date":"2025-08-27","name":"宏景科技","code":"301396","remark":"净买: 8035.93万","price":0,"oprice":0,"cprice":0,"per":0,"per0":0,"per1":0,"per2":0,"per3":0,"per4":0,"per5":0,"per6":0,"per7":0,"per8":0,"per9":0,"per10":0,"per11":0},{"date":"2025-08-28","name":"中国稀土","code":"000831","remark":"净买: 2.31亿","price":0,"oprice":0,"cprice":0,"per":0,"per0":0,"per1":0,"per2":0,"per3":0,"per4":0,"per5":0,"per6":0,"per7":0,"per8":0,"per9":0,"per10":0,"per11":0},{"date":"2025-08-29","name":"中国稀土","code":"000831","remark":"净买: 3.24亿","price":0,"oprice":0,"cprice":0,"per":0,"per0":0,"per1":0,"per2":0,"per3":0,"per4":0,"per5":0,"per6":0,"per7":0,"per8":0,"per9":0,"per10":0,"per11":0},{"date":"2025-09-04","name":"万通发展","code":"600246","remark":"净买: 7658.75万","price":0,"oprice":0,"cprice":0,"per":0,"per0":0,"per1":0,"per2":0,"per3":0,"per4":0,"per5":0,"per6":0,"per7":0,"per8":0,"per9":0,"per10":0,"per11":0},{"date":"2025-09-08","name":"天通股份","code":"600330","remark":"净卖: -6945.09万","price":0,"oprice":0,"cprice":0,"per":0,"per0":0,"per1":0,"per2":0,"per3":0,"per4":0,"per5":0,"per6":0,"per7":0,"per8":0,"per9":0,"per10":0,"per11":0},{"date":"2025-09-11","name":"立讯精密","code":"002475","remark":"净买: 3.26亿","price":0,"oprice":0,"cprice":0,"per":0,"per0":0,"per1":0,"per2":0,"per3":0,"per4":0,"per5":0,"per6":0,"per7":0,"per8":0,"per9":0,"per10":0,"per11":0},{"date":"2025-09-16","name":"同星科技","code":"301252","remark":"净买: 998.22万","price":0,"oprice":0,"cprice":0,"per":0,"per0":0,"per1":0,"per2":0,"per3":0,"per4":0,"per5":0,"per6":0,"per7":0,"per8":0,"per9":0,"per10":0,"per11":0},{"date":"2025-09-23","name":"万向钱潮","code":"000559","remark":"净买: 6701.18万","price":0,"oprice":0,"cprice":0,"per":0,"per0":0,"per1":0,"per2":0,"per3":0,"per4":0,"per5":0,"per6":0,"per7":0,"per8":0,"per9":0,"per10":0,"per11":0},{"date":"2025-09-24","name":"*ST亚太","code":"000691","remark":"净卖: -308.24万","price":0,"oprice":0,"cprice":0,"per":0,"per0":0,"per1":0,"per2":0,"per3":0,"per4":0,"per5":0,"per6":0,"per7":0,"per8":0,"per9":0,"per10":0,"per11":0},{"date":"2025-09-25","name":"上海电气","code":"601727","remark":"净买: 1.96亿","price":0,"oprice":0,"cprice":0,"per":0,"per0":0,"per1":0,"per2":0,"per3":0,"per4":0,"per5":0,"per6":0,"per7":0,"per8":0,"per9":0,"per10":0,"per11":0},{"date":"2025-09-29","name":"天际股份","code":"002759","remark":"净买: 3987.07万","price":0,"oprice":0,"cprice":0,"per":0,"per0":0,"per1":0,"per2":0,"per3":0,"per4":0,"per5":0,"per6":0,"per7":0,"per8":0,"per9":0,"per10":0,"per11":0},{"date":"2025-09-30","name":"天际股份","code":"002759","remark":"净卖: -4401.43万","price":0,"oprice":0,"cprice":0,"per":0,"per0":0,"per1":0,"per2":0,"per3":0,"per4":0,"per5":0,"per6":0,"per7":0,"per8":0,"per9":0,"per10":0,"per11":0},{"date":"2025-10-27","name":"江波龙","code":"301308","remark":"净买: 7568.55万","price":0,"oprice":0,"cprice":0,"per":0,"per0":0,"per1":0,"per2":0,"per3":0,"per4":0,"per5":0,"per6":0,"per7":0,"per8":0,"per9":0,"per10":0,"per11":0},{"date":"2025-10-29","name":"中钨高新","code":"000657","remark":"净买: 5481.34万","price":0,"oprice":0,"cprice":0,"per":0,"per0":0,"per1":0,"per2":0,"per3":0,"per4":0,"per5":0,"per6":0,"per7":0,"per8":0,"per9":0,"per10":0,"per11":0},{"date":"2025-10-30","name":"招商轮船","code":"601872","remark":"净卖: -2083.03万","price":0,"oprice":0,"cprice":0,"per":0,"per0":0,"per1":0,"per2":0,"per3":0,"per4":0,"per5":0,"per6":0,"per7":0,"per8":0,"per9":0,"per10":0,"per11":0},{"date":"2025-11-04","name":"招商轮船","code":"601872","remark":"净卖: -6809.12万","price":0,"oprice":0,"cprice":0,"per":0,"per0":0,"per1":0,"per2":0,"per3":0,"per4":0,"per5":0,"per6":0,"per7":0,"per8":0,"per9":0,"per10":0,"per11":0},{"date":"2025-11-06","name":"德明利","code":"001309","remark":"净卖: -8391.34万","price":0,"oprice":0,"cprice":0,"per":0,"per0":0,"per1":0,"per2":0,"per3":0,"per4":0,"per5":0,"per6":0,"per7":0,"per8":0,"per9":0,"per10":0,"per11":0},{"date":"2025-11-07","name":"多氟多","code":"002407","remark":"净买: 9968.99万","price":0,"oprice":0,"cprice":0,"per":0,"per0":0,"per1":0,"per2":0,"per3":0,"per4":0,"per5":0,"per6":0,"per7":0,"per8":0,"per9":0,"per10":0,"per11":0},{"date":"2025-11-07","name":"兰石重装","code":"603169","remark":"净买: 3878.36万","price":0,"oprice":0,"cprice":0,"per":0,"per0":0,"per1":0,"per2":0,"per3":0,"per4":0,"per5":0,"per6":0,"per7":0,"per8":0,"per9":0,"per10":0,"per11":0},{"date":"2025-11-10","name":"德明利","code":"001309","remark":"净卖: -2.16亿","price":0,"oprice":0,"cprice":0,"per":0,"per0":0,"per1":0,"per2":0,"per3":0,"per4":0,"per5":0,"per6":0,"per7":0,"per8":0,"per9":0,"per10":0,"per11":0},{"date":"2025-11-26","name":"梅雁吉祥","code":"600868","remark":"净买: 1260.84万","price":0,"oprice":0,"cprice":0,"per":0,"per0":0,"per1":0,"per2":0,"per3":0,"per4":0,"per5":0,"per6":0,"per7":0,"per8":0,"per9":0,"per10":0,"per11":0},{"date":"2025-11-26","name":"欢瑞世纪","code":"000892","remark":"净买: 1176.35万","price":0,"oprice":0,"cprice":0,"per":0,"per0":0,"per1":0,"per2":0,"per3":0,"per4":0,"per5":0,"per6":0,"per7":0,"per8":0,"per9":0,"per10":0,"per11":0},{"date":"2025-11-27","name":"雷科防务","code":"002413","remark":"净卖: -4997.61万","price":0,"oprice":0,"cprice":0,"per":0,"per0":0,"per1":0,"per2":0,"per3":0,"per4":0,"per5":0,"per6":0,"per7":0,"per8":0,"per9":0,"per10":0,"per11":0},{"date":"2025-11-28","name":"航天发展","code":"000547","remark":"净买: 6640.78万","price":0,"oprice":0,"cprice":0,"per":0,"per0":0,"per1":0,"per2":0,"per3":0,"per4":0,"per5":0,"per6":0,"per7":0,"per8":0,"per9":0,"per10":0,"per11":0},{"date":"2025-11-28","name":"航天动力","code":"600343","remark":"净买: 7477.60万","price":0,"oprice":0,"cprice":0,"per":0,"per0":0,"per1":0,"per2":0,"per3":0,"per4":0,"per5":0,"per6":0,"per7":0,"per8":0,"per9":0,"per10":0,"per11":0},{"date":"2025-12-01","name":"航天动力","code":"600343","remark":"净卖: -7489.48万","price":0,"oprice":0,"cprice":0,"per":0,"per0":0,"per1":0,"per2":0,"per3":0,"per4":0,"per5":0,"per6":0,"per7":0,"per8":0,"per9":0,"per10":0,"per11":0},{"date":"2025-12-01","name":"榕基软件","code":"002474","remark":"净卖: -2284.01万","price":0,"oprice":0,"cprice":0,"per":0,"per0":0,"per1":0,"per2":0,"per3":0,"per4":0,"per5":0,"per6":0,"per7":0,"per8":0,"per9":0,"per10":0,"per11":0},{"date":"2025-12-01","name":"欢瑞世纪","code":"000892","remark":"净卖: -3142.82万","price":0,"oprice":0,"cprice":0,"per":0,"per0":0,"per1":0,"per2":0,"per3":0,"per4":0,"per5":0,"per6":0,"per7":0,"per8":0,"per9":0,"per10":0,"per11":0},{"date":"2025-12-10","name":"永辉超市","code":"601933","remark":"净买: 4764.53万","price":0,"oprice":0,"cprice":0,"per":0,"per0":0,"per1":0,"per2":0,"per3":0,"per4":0,"per5":0,"per6":0,"per7":0,"per8":0,"per9":0,"per10":0,"per11":0},{"date":"2025-12-15","name":"中国铀业","code":"001280","remark":"净卖: -1.05亿","price":0,"oprice":0,"cprice":0,"per":0,"per0":0,"per1":0,"per2":0,"per3":0,"per4":0,"per5":0,"per6":0,"per7":0,"per8":0,"per9":0,"per10":0,"per11":0},{"date":"2025-12-15","name":"雪人集团","code":"002639","remark":"净卖: -4490.97万","price":0,"oprice":0,"cprice":0,"per":0,"per0":0,"per1":0,"per2":0,"per3":0,"per4":0,"per5":0,"per6":0,"per7":0,"per8":0,"per9":0,"per10":0,"per11":0},{"date":"2025-12-16","name":"星环科技","code":"688031","remark":"净买: 7909.01万","price":0,"oprice":0,"cprice":0,"per":0,"per0":0,"per1":0,"per2":0,"per3":0,"per4":0,"per5":0,"per6":0,"per7":0,"per8":0,"per9":0,"per10":0,"per11":0},{"date":"2025-12-18","name":"海峡创新","code":"300300","remark":"净买: 8055.62万","price":0,"oprice":0,"cprice":0,"per":0,"per0":0,"per1":0,"per2":0,"per3":0,"per4":0,"per5":0,"per6":0,"per7":0,"per8":0,"per9":0,"per10":0,"per11":0},{"date":"2025-12-23","name":"多氟多","code":"002407","remark":"净买: 1.20亿","price":0,"oprice":0,"cprice":0,"per":0,"per0":0,"per1":0,"per2":0,"per3":0,"per4":0,"per5":0,"per6":0,"per7":0,"per8":0,"per9":0,"per10":0,"per11":0},{"date":"2026-01-05","name":"盐湖股份","code":"000792","remark":"净买: 9142.41万","price":0,"oprice":0,"cprice":0,"per":0,"per0":0,"per1":0,"per2":0,"per3":0,"per4":0,"per5":0,"per6":0,"per7":0,"per8":0,"per9":0,"per10":0,"per11":0},{"date":"2026-01-06","name":"农心科技","code":"001231","remark":"净卖: -779.63万","price":0,"oprice":0,"cprice":0,"per":0,"per0":0,"per1":0,"per2":0,"per3":0,"per4":0,"per5":0,"per6":0,"per7":0,"per8":0,"per9":0,"per10":0,"per11":0},{"date":"2026-01-06","name":"星环科技","code":"688031","remark":"净卖: -3476.46万","price":0,"oprice":0,"cprice":0,"per":0,"per0":0,"per1":0,"per2":0,"per3":0,"per4":0,"per5":0,"per6":0,"per7":0,"per8":0,"per9":0,"per10":0,"per11":0},{"date":"2026-01-07","name":"农心科技","code":"001231","remark":"净买: 954.53万","price":0,"oprice":0,"cprice":0,"per":0,"per0":0,"per1":0,"per2":0,"per3":0,"per4":0,"per5":0,"per6":0,"per7":0,"per8":0,"per9":0,"per10":0,"per11":0},{"date":"2026-01-07","name":"快意电梯","code":"002774","remark":"净买: 2442.00万","price":0,"oprice":0,"cprice":0,"per":0,"per0":0,"per1":0,"per2":0,"per3":0,"per4":0,"per5":0,"per6":0,"per7":0,"per8":0,"per9":0,"per10":0,"per11":0},{"date":"2026-01-08","name":"浙江世宝","code":"002703","remark":"净卖: -9588.34万","price":0,"oprice":0,"cprice":0,"per":0,"per0":0,"per1":0,"per2":0,"per3":0,"per4":0,"per5":0,"per6":0,"per7":0,"per8":0,"per9":0,"per10":0,"per11":0},{"date":"2026-01-08","name":"快意电梯","code":"002774","remark":"净买: 2586.35万","price":0,"oprice":0,"cprice":0,"per":0,"per0":0,"per1":0,"per2":0,"per3":0,"per4":0,"per5":0,"per6":0,"per7":0,"per8":0,"per9":0,"per10":0,"per11":0},{"date":"2026-01-08","name":"农心科技","code":"001231","remark":"净卖: -968.48万","price":0,"oprice":0,"cprice":0,"per":0,"per0":0,"per1":0,"per2":0,"per3":0,"per4":0,"per5":0,"per6":0,"per7":0,"per8":0,"per9":0,"per10":0,"per11":0},{"date":"2026-01-12","name":"恒为科技","code":"603496","remark":"净买: 1.07亿","price":0,"oprice":0,"cprice":0,"per":0,"per0":0,"per1":0,"per2":0,"per3":0,"per4":0,"per5":0,"per6":0,"per7":0,"per8":0,"per9":0,"per10":0,"per11":0},{"date":"2026-01-12","name":"快意电梯","code":"002774","remark":"净卖: -5734.55万","price":0,"oprice":0,"cprice":0,"per":0,"per0":0,"per1":0,"per2":0,"per3":0,"per4":0,"per5":0,"per6":0,"per7":0,"per8":0,"per9":0,"per10":0,"per11":0},{"date":"2026-01-12","name":"星环科技","code":"688031","remark":"净卖: -5234.19万","price":0,"oprice":0,"cprice":0,"per":0,"per0":0,"per1":0,"per2":0,"per3":0,"per4":0,"per5":0,"per6":0,"per7":0,"per8":0,"per9":0,"per10":0,"per11":0},{"date":"2026-01-14","name":"快意电梯","code":"002774","remark":"净卖: -5719.25万","price":0,"oprice":0,"cprice":0,"per":0,"per0":0,"per1":0,"per2":0,"per3":0,"per4":0,"per5":0,"per6":0,"per7":0,"per8":0,"per9":0,"per10":0,"per11":0},{"date":"2026-01-16","name":"美年健康","code":"002044","remark":"净卖: -7691.02万","price":0,"oprice":0,"cprice":0,"per":0,"per0":0,"per1":0,"per2":0,"per3":0,"per4":0,"per5":0,"per6":0,"per7":0,"per8":0,"per9":0,"per10":0,"per11":0},{"date":"2026-01-19","name":"博菲电气","code":"001255","remark":"净买: 337.26万","price":0,"oprice":0,"cprice":0,"per":0,"per0":0,"per1":0,"per2":0,"per3":0,"per4":0,"per5":0,"per6":0,"per7":0,"per8":0,"per9":0,"per10":0,"per11":0},{"date":"2026-01-21","name":"博菲电气","code":"001255","remark":"净卖: -1099.01万","price":0,"oprice":0,"cprice":0,"per":0,"per0":0,"per1":0,"per2":0,"per3":0,"per4":0,"per5":0,"per6":0,"per7":0,"per8":0,"per9":0,"per10":0,"per11":0},{"date":"2026-01-23","name":"东方日升","code":"300118","remark":"净买: 6683.06万","price":0,"oprice":0,"cprice":0,"per":0,"per0":0,"per1":0,"per2":0,"per3":0,"per4":0,"per5":0,"per6":0,"per7":0,"per8":0,"per9":0,"per10":0,"per11":0},{"date":"2026-01-23","name":"炬申股份","code":"001202","remark":"净卖: -1915.95万","price":0,"oprice":0,"cprice":0,"per":0,"per0":0,"per1":0,"per2":0,"per3":0,"per4":0,"per5":0,"per6":0,"per7":0,"per8":0,"per9":0,"per10":0,"per11":0},{"date":"2026-01-28","name":"中农联合","code":"003042","remark":"净买: 2051.17万","price":0,"oprice":0,"cprice":0,"per":0,"per0":0,"per1":0,"per2":0,"per3":0,"per4":0,"per5":0,"per6":0,"per7":0,"per8":0,"per9":0,"per10":0,"per11":0},{"date":"2026-01-28","name":"星环科技","code":"688031","remark":"净买: 4873.37万","price":0,"oprice":0,"cprice":0,"per":0,"per0":0,"per1":0,"per2":0,"per3":0,"per4":0,"per5":0,"per6":0,"per7":0,"per8":0,"per9":0,"per10":0,"per11":0},{"date":"2026-01-29","name":"中农联合","code":"003042","remark":"净卖: -1990.65万","price":0,"oprice":0,"cprice":0,"per":0,"per0":0,"per1":0,"per2":0,"per3":0,"per4":0,"per5":0,"per6":0,"per7":0,"per8":0,"per9":0,"per10":0,"per11":0},{"date":"2026-02-02","name":"西上海","code":"605151","remark":"净买: 1141.04万","price":0,"oprice":0,"cprice":0,"per":0,"per0":0,"per1":0,"per2":0,"per3":0,"per4":0,"per5":0,"per6":0,"per7":0,"per8":0,"per9":0,"per10":0,"per11":0},{"date":"2026-02-02","name":"中农联合","code":"003042","remark":"净卖: -2403.99万","price":0,"oprice":0,"cprice":0,"per":0,"per0":0,"per1":0,"per2":0,"per3":0,"per4":0,"per5":0,"per6":0,"per7":0,"per8":0,"per9":0,"per10":0,"per11":0},{"date":"2026-02-04","name":"西上海","code":"605151","remark":"净卖: -501.18万","price":0,"oprice":0,"cprice":0,"per":0,"per0":0,"per1":0,"per2":0,"per3":0,"per4":0,"per5":0,"per6":0,"per7":0,"per8":0,"per9":0,"per10":0,"per11":0},{"date":"2026-02-05","name":"西上海","code":"605151","remark":"净卖: -1735.52万","price":0,"oprice":0,"cprice":0,"per":0,"per0":0,"per1":0,"per2":0,"per3":0,"per4":0,"per5":0,"per6":0,"per7":0,"per8":0,"per9":0,"per10":0,"per11":0},{"date":"2026-02-10","name":"名雕股份","code":"002830","remark":"净卖: -2398.73万","price":0,"oprice":0,"cprice":0,"per":0,"per0":0,"per1":0,"per2":0,"per3":0,"per4":0,"per5":0,"per6":0,"per7":0,"per8":0,"per9":0,"per10":0,"per11":0},{"date":"2026-02-11","name":"德才股份","code":"605287","remark":"净卖: -5203.56万","price":0,"oprice":0,"cprice":0,"per":0,"per0":0,"per1":0,"per2":0,"per3":0,"per4":0,"per5":0,"per6":0,"per7":0,"per8":0,"per9":0,"per10":0,"per11":0},{"date":"2026-02-12","name":"名雕股份","code":"002830","remark":"净卖: -2516.55万","price":0,"oprice":0,"cprice":0,"per":0,"per0":0,"per1":0,"per2":0,"per3":0,"per4":0,"per5":0,"per6":0,"per7":0,"per8":0,"per9":0,"per10":0,"per11":0},{"date":"2026-02-12","name":"首都在线","code":"300846","remark":"净买: 1.53亿","price":0,"oprice":0,"cprice":0,"per":0,"per0":0,"per1":0,"per2":0,"per3":0,"per4":0,"per5":0,"per6":0,"per7":0,"per8":0,"per9":0,"per10":0,"per11":0},{"date":"2026-02-12","name":"美邦股份","code":"605033","remark":"净买: 959.49万","price":0,"oprice":0,"cprice":0,"per":0,"per0":0,"per1":0,"per2":0,"per3":0,"per4":0,"per5":0,"per6":0,"per7":0,"per8":0,"per9":0,"per10":0,"per11":0},{"date":"2026-02-13","name":"首都在线","code":"300846","remark":"净卖: -1.74亿","price":0,"oprice":0,"cprice":0,"per":0,"per0":0,"per1":0,"per2":0,"per3":0,"per4":0,"per5":0,"per6":0,"per7":0,"per8":0,"per9":0,"per10":0,"per11":0},{"date":"2026-02-26","name":"德美化工","code":"002054","remark":"净买: 8640.54万","price":0,"oprice":0,"cprice":0,"per":0,"per0":0,"per1":0,"per2":0,"per3":0,"per4":0,"per5":0,"per6":0,"per7":0,"per8":0,"per9":0,"per10":0,"per11":0},{"date":"2026-02-27","name":"洪兴股份","code":"001209","remark":"净买: 654.90万","price":0,"oprice":0,"cprice":0,"per":0,"per0":0,"per1":0,"per2":0,"per3":0,"per4":0,"per5":0,"per6":0,"per7":0,"per8":0,"per9":0,"per10":0,"per11":0},{"date":"2026-03-02","name":"洪兴股份","code":"001209","remark":"净卖: -520.59万","price":0,"oprice":0,"cprice":0,"per":0,"per0":0,"per1":0,"per2":0,"per3":0,"per4":0,"per5":0,"per6":0,"per7":0,"per8":0,"per9":0,"per10":0,"per11":0},{"date":"2026-03-03","name":"潜能恒信","code":"300191","remark":"净买: 2053.98万","price":0,"oprice":0,"cprice":0,"per":0,"per0":0,"per1":0,"per2":0,"per3":0,"per4":0,"per5":0,"per6":0,"per7":0,"per8":0,"per9":0,"per10":0,"per11":0},{"date":"2026-03-03","name":"星环科技","code":"688031","remark":"净卖: -1.30亿","price":0,"oprice":0,"cprice":0,"per":0,"per0":0,"per1":0,"per2":0,"per3":0,"per4":0,"per5":0,"per6":0,"per7":0,"per8":0,"per9":0,"per10":0,"per11":0},{"date":"2026-03-04","name":"华胜天成","code":"600410","remark":"净卖: -1.27亿","price":0,"oprice":0,"cprice":0,"per":0,"per0":0,"per1":0,"per2":0,"per3":0,"per4":0,"per5":0,"per6":0,"per7":0,"per8":0,"per9":0,"per10":0,"per11":0},{"date":"2026-03-04","name":"王力安防","code":"605268","remark":"净卖: -2780.81万","price":0,"oprice":0,"cprice":0,"per":0,"per0":0,"per1":0,"per2":0,"per3":0,"per4":0,"per5":0,"per6":0,"per7":0,"per8":0,"per9":0,"per10":0,"per11":0},{"date":"2026-03-05","name":"王力安防","code":"605268","remark":"净卖: -2780.81万","price":0,"oprice":0,"cprice":0,"per":0,"per0":0,"per1":0,"per2":0,"per3":0,"per4":0,"per5":0,"per6":0,"per7":0,"per8":0,"per9":0,"per10":0,"per11":0},{"date":"2026-03-09","name":"首都在线","code":"300846","remark":"净买: 1.12亿","price":0,"oprice":0,"cprice":0,"per":0,"per0":0,"per1":0,"per2":0,"per3":0,"per4":0,"per5":0,"per6":0,"per7":0,"per8":0,"per9":0,"per10":0,"per11":0},{"date":"2026-03-09","name":"王力安防","code":"605268","remark":"净买: 1127.67万","price":0,"oprice":0,"cprice":0,"per":0,"per0":0,"per1":0,"per2":0,"per3":0,"per4":0,"per5":0,"per6":0,"per7":0,"per8":0,"per9":0,"per10":0,"per11":0},{"date":"2026-03-10","name":"洲际油气","code":"600759","remark":"净卖: -6693.46万","price":0,"oprice":0,"cprice":0,"per":0,"per0":0,"per1":0,"per2":0,"per3":0,"per4":0,"per5":0,"per6":0,"per7":0,"per8":0,"per9":0,"per10":0,"per11":0},{"date":"2026-03-10","name":"首都在线","code":"300846","remark":"净卖: -1.13亿","price":0,"oprice":0,"cprice":0,"per":0,"per0":0,"per1":0,"per2":0,"per3":0,"per4":0,"per5":0,"per6":0,"per7":0,"per8":0,"per9":0,"per10":0,"per11":0},{"date":"2026-03-16","name":"金牛化工","code":"600722","remark":"净卖: -1.02亿","price":0,"oprice":0,"cprice":0,"per":0,"per0":0,"per1":0,"per2":0,"per3":0,"per4":0,"per5":0,"per6":0,"per7":0,"per8":0,"per9":0,"per10":0,"per11":0},{"date":"2026-03-30","name":"百川股份","code":"002455","remark":"净买: 8554.94万","price":0,"oprice":0,"cprice":0,"per":0,"per0":0,"per1":0,"per2":0,"per3":0,"per4":0,"per5":0,"per6":0,"per7":0,"per8":0,"per9":0,"per10":0,"per11":0},{"date":"2026-04-08","name":"中油资本","code":"000617","remark":"净卖: -1.17亿","price":0,"oprice":0,"cprice":0,"per":0,"per0":0,"per1":0,"per2":0,"per3":0,"per4":0,"per5":0,"per6":0,"per7":0,"per8":0,"per9":0,"per10":0,"per11":0},{"date":"2026-04-16","name":"长信科技","code":"300088","remark":"净买: 1.95亿","price":0,"oprice":0,"cprice":0,"per":0,"per0":0,"per1":0,"per2":0,"per3":0,"per4":0,"per5":0,"per6":0,"per7":0,"per8":0,"per9":0,"per10":0,"per11":0}]